{
  "source_file": "1g7nz0dm.tkk",
  "full_name": "Ford Performance Racing School FPRS Infield",
  "name": "Ford Performance Racing School",
  "venue_id": "1g7nz0dm",
  "short_name": "FPRS Infield",
  "country": "US",
  "track_length_m": 1822.4,
  "reference_point": {
    "lat": 35.3501225,
    "lon": -80.6832098,
    "alt_m": 0.0
  },
  "start_finish": {
    "lat": 35.3518401,
    "lon": -80.6825241
  },
  "surface": "asphalt",
  "timezone": "America/New_York",
  "timezone_label": "(UTC-05:00) Eastern Time (US & Canada)",
  "contact": {
    "city": "Concord",
    "address": "5115 Morehead Road",
    "postal_code": "28027",
    "phone": "+1 435 277 7333",
    "url": "https://www.fordperformanceracingschool.com/"
  },
  "start_finish_line": {
    "p1": {
      "lat": 35.3519311,
      "lon": -80.6825742
    },
    "p2": {
      "lat": 35.3517491,
      "lon": -80.682474
    }
  },
  "logo_file": "Ford Performance Racing School FPRS Infield_logo.png",
  "svg_file": "Ford Performance Racing School FPRS Infield.svg",
  "gps_points": [
    {
      "lat": 35.3518401,
      "lon": -80.6825241,
      "alt_m": 0.0
    },
    {
      "lat": 35.3518474,
      "lon": -80.6825042,
      "alt_m": 0.0
    },
    {
      "lat": 35.3518566,
      "lon": -80.6824767,
      "alt_m": 0.0
    },
    {
      "lat": 35.3518648,
      "lon": -80.6824487,
      "alt_m": 0.0
    },
    {
      "lat": 35.3518725,
      "lon": -80.6824209,
      "alt_m": 0.0
    },
    {
      "lat": 35.3518795,
      "lon": -80.6823928,
      "alt_m": 0.0
    },
    {
      "lat": 35.3518859,
      "lon": -80.6823641,
      "alt_m": 0.0
    },
    {
      "lat": 35.3518916,
      "lon": -80.6823355,
      "alt_m": 0.0
    },
    {
      "lat": 35.3518968,
      "lon": -80.6823066,
      "alt_m": 0.0
    },
    {
      "lat": 35.3519015,
      "lon": -80.6822774,
      "alt_m": 0.0
    },
    {
      "lat": 35.3519057,
      "lon": -80.6822481,
      "alt_m": 0.0
    },
    {
      "lat": 35.3519092,
      "lon": -80.6822187,
      "alt_m": 0.0
    },
    {
      "lat": 35.3519121,
      "lon": -80.682189,
      "alt_m": 0.0
    },
    {
      "lat": 35.3519142,
      "lon": -80.6821591,
      "alt_m": 0.0
    },
    {
      "lat": 35.3519158,
      "lon": -80.682129,
      "alt_m": 0.0
    },
    {
      "lat": 35.3519168,
      "lon": -80.6820989,
      "alt_m": 0.0
    },
    {
      "lat": 35.3519174,
      "lon": -80.6820687,
      "alt_m": 0.0
    },
    {
      "lat": 35.3519173,
      "lon": -80.6820387,
      "alt_m": 0.0
    },
    {
      "lat": 35.3519164,
      "lon": -80.6820091,
      "alt_m": 0.0
    },
    {
      "lat": 35.3519152,
      "lon": -80.6819798,
      "alt_m": 0.0
    },
    {
      "lat": 35.3519135,
      "lon": -80.6819506,
      "alt_m": 0.0
    },
    {
      "lat": 35.3519113,
      "lon": -80.6819219,
      "alt_m": 0.0
    },
    {
      "lat": 35.3519084,
      "lon": -80.6818935,
      "alt_m": 0.0
    },
    {
      "lat": 35.3519047,
      "lon": -80.6818655,
      "alt_m": 0.0
    },
    {
      "lat": 35.3519005,
      "lon": -80.6818376,
      "alt_m": 0.0
    },
    {
      "lat": 35.3518958,
      "lon": -80.68181,
      "alt_m": 0.0
    },
    {
      "lat": 35.3518903,
      "lon": -80.6817828,
      "alt_m": 0.0
    },
    {
      "lat": 35.3518844,
      "lon": -80.6817557,
      "alt_m": 0.0
    },
    {
      "lat": 35.3518779,
      "lon": -80.6817286,
      "alt_m": 0.0
    },
    {
      "lat": 35.351871,
      "lon": -80.6817018,
      "alt_m": 0.0
    },
    {
      "lat": 35.3518635,
      "lon": -80.6816752,
      "alt_m": 0.0
    },
    {
      "lat": 35.3518554,
      "lon": -80.6816489,
      "alt_m": 0.0
    },
    {
      "lat": 35.3518467,
      "lon": -80.6816228,
      "alt_m": 0.0
    },
    {
      "lat": 35.3518374,
      "lon": -80.6815971,
      "alt_m": 0.0
    },
    {
      "lat": 35.3518275,
      "lon": -80.6815718,
      "alt_m": 0.0
    },
    {
      "lat": 35.3518169,
      "lon": -80.6815469,
      "alt_m": 0.0
    },
    {
      "lat": 35.3518057,
      "lon": -80.6815225,
      "alt_m": 0.0
    },
    {
      "lat": 35.3517938,
      "lon": -80.6814988,
      "alt_m": 0.0
    },
    {
      "lat": 35.3517814,
      "lon": -80.6814755,
      "alt_m": 0.0
    },
    {
      "lat": 35.3517684,
      "lon": -80.6814528,
      "alt_m": 0.0
    },
    {
      "lat": 35.3517549,
      "lon": -80.6814308,
      "alt_m": 0.0
    },
    {
      "lat": 35.3517409,
      "lon": -80.6814094,
      "alt_m": 0.0
    },
    {
      "lat": 35.3517263,
      "lon": -80.6813885,
      "alt_m": 0.0
    },
    {
      "lat": 35.3517111,
      "lon": -80.6813684,
      "alt_m": 0.0
    },
    {
      "lat": 35.3516953,
      "lon": -80.681349,
      "alt_m": 0.0
    },
    {
      "lat": 35.3516789,
      "lon": -80.6813303,
      "alt_m": 0.0
    },
    {
      "lat": 35.3516623,
      "lon": -80.6813124,
      "alt_m": 0.0
    },
    {
      "lat": 35.3516452,
      "lon": -80.6812953,
      "alt_m": 0.0
    },
    {
      "lat": 35.3516275,
      "lon": -80.6812794,
      "alt_m": 0.0
    },
    {
      "lat": 35.3516095,
      "lon": -80.6812645,
      "alt_m": 0.0
    },
    {
      "lat": 35.3515908,
      "lon": -80.6812506,
      "alt_m": 0.0
    },
    {
      "lat": 35.3515718,
      "lon": -80.6812374,
      "alt_m": 0.0
    },
    {
      "lat": 35.3515527,
      "lon": -80.6812251,
      "alt_m": 0.0
    },
    {
      "lat": 35.3515332,
      "lon": -80.6812137,
      "alt_m": 0.0
    },
    {
      "lat": 35.3515135,
      "lon": -80.6812034,
      "alt_m": 0.0
    },
    {
      "lat": 35.3514932,
      "lon": -80.6811941,
      "alt_m": 0.0
    },
    {
      "lat": 35.3514729,
      "lon": -80.6811856,
      "alt_m": 0.0
    },
    {
      "lat": 35.3514525,
      "lon": -80.6811778,
      "alt_m": 0.0
    },
    {
      "lat": 35.351432,
      "lon": -80.6811707,
      "alt_m": 0.0
    },
    {
      "lat": 35.3514114,
      "lon": -80.6811646,
      "alt_m": 0.0
    },
    {
      "lat": 35.3513907,
      "lon": -80.6811594,
      "alt_m": 0.0
    },
    {
      "lat": 35.3513698,
      "lon": -80.6811552,
      "alt_m": 0.0
    },
    {
      "lat": 35.351349,
      "lon": -80.6811521,
      "alt_m": 0.0
    },
    {
      "lat": 35.3513283,
      "lon": -80.6811499,
      "alt_m": 0.0
    },
    {
      "lat": 35.3513073,
      "lon": -80.6811486,
      "alt_m": 0.0
    },
    {
      "lat": 35.3512861,
      "lon": -80.681148,
      "alt_m": 0.0
    },
    {
      "lat": 35.351265,
      "lon": -80.6811486,
      "alt_m": 0.0
    },
    {
      "lat": 35.3512438,
      "lon": -80.6811501,
      "alt_m": 0.0
    },
    {
      "lat": 35.3512224,
      "lon": -80.6811522,
      "alt_m": 0.0
    },
    {
      "lat": 35.3512007,
      "lon": -80.681155,
      "alt_m": 0.0
    },
    {
      "lat": 35.3511791,
      "lon": -80.6811586,
      "alt_m": 0.0
    },
    {
      "lat": 35.3511574,
      "lon": -80.681163,
      "alt_m": 0.0
    },
    {
      "lat": 35.3511354,
      "lon": -80.6811677,
      "alt_m": 0.0
    },
    {
      "lat": 35.3511131,
      "lon": -80.6811731,
      "alt_m": 0.0
    },
    {
      "lat": 35.3510908,
      "lon": -80.6811789,
      "alt_m": 0.0
    },
    {
      "lat": 35.3510682,
      "lon": -80.6811852,
      "alt_m": 0.0
    },
    {
      "lat": 35.3510454,
      "lon": -80.681192,
      "alt_m": 0.0
    },
    {
      "lat": 35.3510222,
      "lon": -80.681199,
      "alt_m": 0.0
    },
    {
      "lat": 35.3509987,
      "lon": -80.6812062,
      "alt_m": 0.0
    },
    {
      "lat": 35.350975,
      "lon": -80.6812135,
      "alt_m": 0.0
    },
    {
      "lat": 35.3509508,
      "lon": -80.6812209,
      "alt_m": 0.0
    },
    {
      "lat": 35.3509264,
      "lon": -80.6812286,
      "alt_m": 0.0
    },
    {
      "lat": 35.3509018,
      "lon": -80.6812362,
      "alt_m": 0.0
    },
    {
      "lat": 35.3508767,
      "lon": -80.6812439,
      "alt_m": 0.0
    },
    {
      "lat": 35.3508513,
      "lon": -80.6812516,
      "alt_m": 0.0
    },
    {
      "lat": 35.3508257,
      "lon": -80.6812596,
      "alt_m": 0.0
    },
    {
      "lat": 35.3507997,
      "lon": -80.6812676,
      "alt_m": 0.0
    },
    {
      "lat": 35.3507735,
      "lon": -80.6812757,
      "alt_m": 0.0
    },
    {
      "lat": 35.3507468,
      "lon": -80.681284,
      "alt_m": 0.0
    },
    {
      "lat": 35.35072,
      "lon": -80.6812925,
      "alt_m": 0.0
    },
    {
      "lat": 35.3506926,
      "lon": -80.6813011,
      "alt_m": 0.0
    },
    {
      "lat": 35.3506651,
      "lon": -80.6813099,
      "alt_m": 0.0
    },
    {
      "lat": 35.3506373,
      "lon": -80.6813188,
      "alt_m": 0.0
    },
    {
      "lat": 35.3506091,
      "lon": -80.6813277,
      "alt_m": 0.0
    },
    {
      "lat": 35.3505806,
      "lon": -80.6813369,
      "alt_m": 0.0
    },
    {
      "lat": 35.3505521,
      "lon": -80.6813462,
      "alt_m": 0.0
    },
    {
      "lat": 35.3505233,
      "lon": -80.6813555,
      "alt_m": 0.0
    },
    {
      "lat": 35.3504951,
      "lon": -80.6813647,
      "alt_m": 0.0
    },
    {
      "lat": 35.3504672,
      "lon": -80.6813739,
      "alt_m": 0.0
    },
    {
      "lat": 35.3504399,
      "lon": -80.6813829,
      "alt_m": 0.0
    },
    {
      "lat": 35.3504131,
      "lon": -80.681392,
      "alt_m": 0.0
    },
    {
      "lat": 35.3503868,
      "lon": -80.6814009,
      "alt_m": 0.0
    },
    {
      "lat": 35.3503607,
      "lon": -80.6814098,
      "alt_m": 0.0
    },
    {
      "lat": 35.3503354,
      "lon": -80.6814187,
      "alt_m": 0.0
    },
    {
      "lat": 35.3503105,
      "lon": -80.6814277,
      "alt_m": 0.0
    },
    {
      "lat": 35.3502861,
      "lon": -80.681437,
      "alt_m": 0.0
    },
    {
      "lat": 35.3502624,
      "lon": -80.6814466,
      "alt_m": 0.0
    },
    {
      "lat": 35.3502393,
      "lon": -80.6814565,
      "alt_m": 0.0
    },
    {
      "lat": 35.3502165,
      "lon": -80.6814668,
      "alt_m": 0.0
    },
    {
      "lat": 35.350194,
      "lon": -80.6814776,
      "alt_m": 0.0
    },
    {
      "lat": 35.3501722,
      "lon": -80.681489,
      "alt_m": 0.0
    },
    {
      "lat": 35.3501508,
      "lon": -80.6815008,
      "alt_m": 0.0
    },
    {
      "lat": 35.3501299,
      "lon": -80.6815133,
      "alt_m": 0.0
    },
    {
      "lat": 35.3501096,
      "lon": -80.6815263,
      "alt_m": 0.0
    },
    {
      "lat": 35.3500897,
      "lon": -80.6815397,
      "alt_m": 0.0
    },
    {
      "lat": 35.3500704,
      "lon": -80.6815535,
      "alt_m": 0.0
    },
    {
      "lat": 35.3500515,
      "lon": -80.6815679,
      "alt_m": 0.0
    },
    {
      "lat": 35.3500331,
      "lon": -80.6815826,
      "alt_m": 0.0
    },
    {
      "lat": 35.3500155,
      "lon": -80.6815978,
      "alt_m": 0.0
    },
    {
      "lat": 35.3499982,
      "lon": -80.6816135,
      "alt_m": 0.0
    },
    {
      "lat": 35.3499815,
      "lon": -80.6816298,
      "alt_m": 0.0
    },
    {
      "lat": 35.3499654,
      "lon": -80.6816466,
      "alt_m": 0.0
    },
    {
      "lat": 35.3499498,
      "lon": -80.6816639,
      "alt_m": 0.0
    },
    {
      "lat": 35.3499349,
      "lon": -80.6816817,
      "alt_m": 0.0
    },
    {
      "lat": 35.3499208,
      "lon": -80.6816998,
      "alt_m": 0.0
    },
    {
      "lat": 35.3499072,
      "lon": -80.6817185,
      "alt_m": 0.0
    },
    {
      "lat": 35.3498944,
      "lon": -80.6817379,
      "alt_m": 0.0
    },
    {
      "lat": 35.3498824,
      "lon": -80.6817574,
      "alt_m": 0.0
    },
    {
      "lat": 35.349871,
      "lon": -80.6817774,
      "alt_m": 0.0
    },
    {
      "lat": 35.3498603,
      "lon": -80.6817976,
      "alt_m": 0.0
    },
    {
      "lat": 35.3498504,
      "lon": -80.6818184,
      "alt_m": 0.0
    },
    {
      "lat": 35.3498413,
      "lon": -80.6818396,
      "alt_m": 0.0
    },
    {
      "lat": 35.3498329,
      "lon": -80.6818613,
      "alt_m": 0.0
    },
    {
      "lat": 35.3498253,
      "lon": -80.6818833,
      "alt_m": 0.0
    },
    {
      "lat": 35.3498184,
      "lon": -80.6819057,
      "alt_m": 0.0
    },
    {
      "lat": 35.3498123,
      "lon": -80.6819283,
      "alt_m": 0.0
    },
    {
      "lat": 35.3498071,
      "lon": -80.6819516,
      "alt_m": 0.0
    },
    {
      "lat": 35.3498024,
      "lon": -80.6819752,
      "alt_m": 0.0
    },
    {
      "lat": 35.3497984,
      "lon": -80.6819993,
      "alt_m": 0.0
    },
    {
      "lat": 35.349795,
      "lon": -80.6820236,
      "alt_m": 0.0
    },
    {
      "lat": 35.3497924,
      "lon": -80.6820483,
      "alt_m": 0.0
    },
    {
      "lat": 35.3497903,
      "lon": -80.6820735,
      "alt_m": 0.0
    },
    {
      "lat": 35.349789,
      "lon": -80.6820988,
      "alt_m": 0.0
    },
    {
      "lat": 35.3497882,
      "lon": -80.6821244,
      "alt_m": 0.0
    },
    {
      "lat": 35.3497881,
      "lon": -80.6821505,
      "alt_m": 0.0
    },
    {
      "lat": 35.3497885,
      "lon": -80.6821768,
      "alt_m": 0.0
    },
    {
      "lat": 35.3497895,
      "lon": -80.6822032,
      "alt_m": 0.0
    },
    {
      "lat": 35.3497912,
      "lon": -80.6822299,
      "alt_m": 0.0
    },
    {
      "lat": 35.3497935,
      "lon": -80.6822568,
      "alt_m": 0.0
    },
    {
      "lat": 35.3497962,
      "lon": -80.682284,
      "alt_m": 0.0
    },
    {
      "lat": 35.3497995,
      "lon": -80.6823113,
      "alt_m": 0.0
    },
    {
      "lat": 35.3498034,
      "lon": -80.6823389,
      "alt_m": 0.0
    },
    {
      "lat": 35.3498076,
      "lon": -80.6823665,
      "alt_m": 0.0
    },
    {
      "lat": 35.3498123,
      "lon": -80.6823946,
      "alt_m": 0.0
    },
    {
      "lat": 35.3498175,
      "lon": -80.6824227,
      "alt_m": 0.0
    },
    {
      "lat": 35.349823,
      "lon": -80.6824512,
      "alt_m": 0.0
    },
    {
      "lat": 35.3498289,
      "lon": -80.6824798,
      "alt_m": 0.0
    },
    {
      "lat": 35.3498351,
      "lon": -80.6825088,
      "alt_m": 0.0
    },
    {
      "lat": 35.3498415,
      "lon": -80.6825381,
      "alt_m": 0.0
    },
    {
      "lat": 35.349848,
      "lon": -80.6825678,
      "alt_m": 0.0
    },
    {
      "lat": 35.3498545,
      "lon": -80.6825976,
      "alt_m": 0.0
    },
    {
      "lat": 35.3498607,
      "lon": -80.6826271,
      "alt_m": 0.0
    },
    {
      "lat": 35.3498668,
      "lon": -80.6826561,
      "alt_m": 0.0
    },
    {
      "lat": 35.3498728,
      "lon": -80.6826845,
      "alt_m": 0.0
    },
    {
      "lat": 35.3498783,
      "lon": -80.6827125,
      "alt_m": 0.0
    },
    {
      "lat": 35.3498835,
      "lon": -80.6827402,
      "alt_m": 0.0
    },
    {
      "lat": 35.3498884,
      "lon": -80.6827676,
      "alt_m": 0.0
    },
    {
      "lat": 35.3498929,
      "lon": -80.6827947,
      "alt_m": 0.0
    },
    {
      "lat": 35.349897,
      "lon": -80.6828214,
      "alt_m": 0.0
    },
    {
      "lat": 35.3499005,
      "lon": -80.6828479,
      "alt_m": 0.0
    },
    {
      "lat": 35.3499035,
      "lon": -80.6828739,
      "alt_m": 0.0
    },
    {
      "lat": 35.3499059,
      "lon": -80.6828996,
      "alt_m": 0.0
    },
    {
      "lat": 35.3499076,
      "lon": -80.6829248,
      "alt_m": 0.0
    },
    {
      "lat": 35.3499087,
      "lon": -80.6829497,
      "alt_m": 0.0
    },
    {
      "lat": 35.3499092,
      "lon": -80.6829739,
      "alt_m": 0.0
    },
    {
      "lat": 35.349909,
      "lon": -80.6829976,
      "alt_m": 0.0
    },
    {
      "lat": 35.3499081,
      "lon": -80.6830208,
      "alt_m": 0.0
    },
    {
      "lat": 35.3499064,
      "lon": -80.6830436,
      "alt_m": 0.0
    },
    {
      "lat": 35.3499041,
      "lon": -80.6830659,
      "alt_m": 0.0
    },
    {
      "lat": 35.3499013,
      "lon": -80.6830879,
      "alt_m": 0.0
    },
    {
      "lat": 35.3498976,
      "lon": -80.6831097,
      "alt_m": 0.0
    },
    {
      "lat": 35.3498932,
      "lon": -80.6831313,
      "alt_m": 0.0
    },
    {
      "lat": 35.3498883,
      "lon": -80.6831526,
      "alt_m": 0.0
    },
    {
      "lat": 35.3498827,
      "lon": -80.6831734,
      "alt_m": 0.0
    },
    {
      "lat": 35.3498762,
      "lon": -80.6831939,
      "alt_m": 0.0
    },
    {
      "lat": 35.3498692,
      "lon": -80.6832137,
      "alt_m": 0.0
    },
    {
      "lat": 35.3498615,
      "lon": -80.6832329,
      "alt_m": 0.0
    },
    {
      "lat": 35.3498531,
      "lon": -80.6832515,
      "alt_m": 0.0
    },
    {
      "lat": 35.3498441,
      "lon": -80.6832694,
      "alt_m": 0.0
    },
    {
      "lat": 35.3498343,
      "lon": -80.6832867,
      "alt_m": 0.0
    },
    {
      "lat": 35.3498241,
      "lon": -80.6833033,
      "alt_m": 0.0
    },
    {
      "lat": 35.3498132,
      "lon": -80.6833191,
      "alt_m": 0.0
    },
    {
      "lat": 35.3498019,
      "lon": -80.6833342,
      "alt_m": 0.0
    },
    {
      "lat": 35.3497901,
      "lon": -80.6833484,
      "alt_m": 0.0
    },
    {
      "lat": 35.3497778,
      "lon": -80.6833615,
      "alt_m": 0.0
    },
    {
      "lat": 35.349765,
      "lon": -80.683374,
      "alt_m": 0.0
    },
    {
      "lat": 35.3497517,
      "lon": -80.6833856,
      "alt_m": 0.0
    },
    {
      "lat": 35.349738,
      "lon": -80.6833966,
      "alt_m": 0.0
    },
    {
      "lat": 35.3497239,
      "lon": -80.6834066,
      "alt_m": 0.0
    },
    {
      "lat": 35.3497094,
      "lon": -80.6834155,
      "alt_m": 0.0
    },
    {
      "lat": 35.3496946,
      "lon": -80.6834237,
      "alt_m": 0.0
    },
    {
      "lat": 35.3496796,
      "lon": -80.6834311,
      "alt_m": 0.0
    },
    {
      "lat": 35.3496641,
      "lon": -80.6834374,
      "alt_m": 0.0
    },
    {
      "lat": 35.3496483,
      "lon": -80.683443,
      "alt_m": 0.0
    },
    {
      "lat": 35.3496326,
      "lon": -80.6834475,
      "alt_m": 0.0
    },
    {
      "lat": 35.3496165,
      "lon": -80.683451,
      "alt_m": 0.0
    },
    {
      "lat": 35.3496003,
      "lon": -80.6834537,
      "alt_m": 0.0
    },
    {
      "lat": 35.3495842,
      "lon": -80.6834553,
      "alt_m": 0.0
    },
    {
      "lat": 35.3495678,
      "lon": -80.6834562,
      "alt_m": 0.0
    },
    {
      "lat": 35.3495514,
      "lon": -80.6834561,
      "alt_m": 0.0
    },
    {
      "lat": 35.349535,
      "lon": -80.683455,
      "alt_m": 0.0
    },
    {
      "lat": 35.3495186,
      "lon": -80.683453,
      "alt_m": 0.0
    },
    {
      "lat": 35.3495023,
      "lon": -80.6834501,
      "alt_m": 0.0
    },
    {
      "lat": 35.3494859,
      "lon": -80.6834461,
      "alt_m": 0.0
    },
    {
      "lat": 35.3494696,
      "lon": -80.6834413,
      "alt_m": 0.0
    },
    {
      "lat": 35.3494534,
      "lon": -80.6834356,
      "alt_m": 0.0
    },
    {
      "lat": 35.3494375,
      "lon": -80.6834288,
      "alt_m": 0.0
    },
    {
      "lat": 35.3494218,
      "lon": -80.6834211,
      "alt_m": 0.0
    },
    {
      "lat": 35.3494063,
      "lon": -80.6834127,
      "alt_m": 0.0
    },
    {
      "lat": 35.3493911,
      "lon": -80.6834033,
      "alt_m": 0.0
    },
    {
      "lat": 35.3493764,
      "lon": -80.683393,
      "alt_m": 0.0
    },
    {
      "lat": 35.349362,
      "lon": -80.6833818,
      "alt_m": 0.0
    },
    {
      "lat": 35.349348,
      "lon": -80.6833699,
      "alt_m": 0.0
    },
    {
      "lat": 35.3493347,
      "lon": -80.683357,
      "alt_m": 0.0
    },
    {
      "lat": 35.3493219,
      "lon": -80.6833436,
      "alt_m": 0.0
    },
    {
      "lat": 35.3493099,
      "lon": -80.6833294,
      "alt_m": 0.0
    },
    {
      "lat": 35.3492984,
      "lon": -80.6833145,
      "alt_m": 0.0
    },
    {
      "lat": 35.3492875,
      "lon": -80.6832989,
      "alt_m": 0.0
    },
    {
      "lat": 35.3492773,
      "lon": -80.6832826,
      "alt_m": 0.0
    },
    {
      "lat": 35.3492679,
      "lon": -80.6832659,
      "alt_m": 0.0
    },
    {
      "lat": 35.349259,
      "lon": -80.6832487,
      "alt_m": 0.0
    },
    {
      "lat": 35.3492509,
      "lon": -80.6832311,
      "alt_m": 0.0
    },
    {
      "lat": 35.3492437,
      "lon": -80.6832133,
      "alt_m": 0.0
    },
    {
      "lat": 35.3492371,
      "lon": -80.6831951,
      "alt_m": 0.0
    },
    {
      "lat": 35.3492315,
      "lon": -80.6831765,
      "alt_m": 0.0
    },
    {
      "lat": 35.3492266,
      "lon": -80.6831578,
      "alt_m": 0.0
    },
    {
      "lat": 35.3492225,
      "lon": -80.683139,
      "alt_m": 0.0
    },
    {
      "lat": 35.3492191,
      "lon": -80.6831198,
      "alt_m": 0.0
    },
    {
      "lat": 35.3492164,
      "lon": -80.6831004,
      "alt_m": 0.0
    },
    {
      "lat": 35.3492144,
      "lon": -80.6830807,
      "alt_m": 0.0
    },
    {
      "lat": 35.3492132,
      "lon": -80.6830608,
      "alt_m": 0.0
    },
    {
      "lat": 35.3492128,
      "lon": -80.6830409,
      "alt_m": 0.0
    },
    {
      "lat": 35.3492132,
      "lon": -80.6830209,
      "alt_m": 0.0
    },
    {
      "lat": 35.3492144,
      "lon": -80.683001,
      "alt_m": 0.0
    },
    {
      "lat": 35.3492165,
      "lon": -80.6829809,
      "alt_m": 0.0
    },
    {
      "lat": 35.3492192,
      "lon": -80.6829608,
      "alt_m": 0.0
    },
    {
      "lat": 35.3492227,
      "lon": -80.6829408,
      "alt_m": 0.0
    },
    {
      "lat": 35.349227,
      "lon": -80.6829204,
      "alt_m": 0.0
    },
    {
      "lat": 35.3492321,
      "lon": -80.6829004,
      "alt_m": 0.0
    },
    {
      "lat": 35.3492377,
      "lon": -80.6828803,
      "alt_m": 0.0
    },
    {
      "lat": 35.3492441,
      "lon": -80.6828603,
      "alt_m": 0.0
    },
    {
      "lat": 35.3492513,
      "lon": -80.6828402,
      "alt_m": 0.0
    },
    {
      "lat": 35.3492591,
      "lon": -80.6828199,
      "alt_m": 0.0
    },
    {
      "lat": 35.3492678,
      "lon": -80.6827995,
      "alt_m": 0.0
    },
    {
      "lat": 35.3492771,
      "lon": -80.6827791,
      "alt_m": 0.0
    },
    {
      "lat": 35.3492868,
      "lon": -80.6827587,
      "alt_m": 0.0
    },
    {
      "lat": 35.349297,
      "lon": -80.682738,
      "alt_m": 0.0
    },
    {
      "lat": 35.3493077,
      "lon": -80.6827173,
      "alt_m": 0.0
    },
    {
      "lat": 35.3493189,
      "lon": -80.6826963,
      "alt_m": 0.0
    },
    {
      "lat": 35.3493304,
      "lon": -80.6826752,
      "alt_m": 0.0
    },
    {
      "lat": 35.3493419,
      "lon": -80.682654,
      "alt_m": 0.0
    },
    {
      "lat": 35.3493533,
      "lon": -80.6826332,
      "alt_m": 0.0
    },
    {
      "lat": 35.3493641,
      "lon": -80.6826128,
      "alt_m": 0.0
    },
    {
      "lat": 35.3493745,
      "lon": -80.6825925,
      "alt_m": 0.0
    },
    {
      "lat": 35.3493844,
      "lon": -80.6825727,
      "alt_m": 0.0
    },
    {
      "lat": 35.3493937,
      "lon": -80.6825533,
      "alt_m": 0.0
    },
    {
      "lat": 35.3494024,
      "lon": -80.6825339,
      "alt_m": 0.0
    },
    {
      "lat": 35.3494104,
      "lon": -80.6825146,
      "alt_m": 0.0
    },
    {
      "lat": 35.3494177,
      "lon": -80.6824955,
      "alt_m": 0.0
    },
    {
      "lat": 35.3494241,
      "lon": -80.6824765,
      "alt_m": 0.0
    },
    {
      "lat": 35.3494299,
      "lon": -80.6824574,
      "alt_m": 0.0
    },
    {
      "lat": 35.3494349,
      "lon": -80.6824381,
      "alt_m": 0.0
    },
    {
      "lat": 35.3494391,
      "lon": -80.6824188,
      "alt_m": 0.0
    },
    {
      "lat": 35.3494424,
      "lon": -80.6823993,
      "alt_m": 0.0
    },
    {
      "lat": 35.3494452,
      "lon": -80.6823798,
      "alt_m": 0.0
    },
    {
      "lat": 35.349447,
      "lon": -80.6823602,
      "alt_m": 0.0
    },
    {
      "lat": 35.3494482,
      "lon": -80.6823404,
      "alt_m": 0.0
    },
    {
      "lat": 35.3494485,
      "lon": -80.6823206,
      "alt_m": 0.0
    },
    {
      "lat": 35.3494479,
      "lon": -80.6823007,
      "alt_m": 0.0
    },
    {
      "lat": 35.3494462,
      "lon": -80.6822812,
      "alt_m": 0.0
    },
    {
      "lat": 35.3494437,
      "lon": -80.6822621,
      "alt_m": 0.0
    },
    {
      "lat": 35.3494403,
      "lon": -80.6822429,
      "alt_m": 0.0
    },
    {
      "lat": 35.3494359,
      "lon": -80.6822241,
      "alt_m": 0.0
    },
    {
      "lat": 35.349431,
      "lon": -80.6822054,
      "alt_m": 0.0
    },
    {
      "lat": 35.3494252,
      "lon": -80.6821872,
      "alt_m": 0.0
    },
    {
      "lat": 35.3494183,
      "lon": -80.6821696,
      "alt_m": 0.0
    },
    {
      "lat": 35.3494107,
      "lon": -80.6821524,
      "alt_m": 0.0
    },
    {
      "lat": 35.3494025,
      "lon": -80.6821351,
      "alt_m": 0.0
    },
    {
      "lat": 35.3493937,
      "lon": -80.6821188,
      "alt_m": 0.0
    },
    {
      "lat": 35.3493838,
      "lon": -80.6821032,
      "alt_m": 0.0
    },
    {
      "lat": 35.3493735,
      "lon": -80.682088,
      "alt_m": 0.0
    },
    {
      "lat": 35.3493626,
      "lon": -80.6820736,
      "alt_m": 0.0
    },
    {
      "lat": 35.3493508,
      "lon": -80.6820601,
      "alt_m": 0.0
    },
    {
      "lat": 35.3493385,
      "lon": -80.6820475,
      "alt_m": 0.0
    },
    {
      "lat": 35.3493258,
      "lon": -80.6820353,
      "alt_m": 0.0
    },
    {
      "lat": 35.3493126,
      "lon": -80.6820241,
      "alt_m": 0.0
    },
    {
      "lat": 35.349299,
      "lon": -80.6820135,
      "alt_m": 0.0
    },
    {
      "lat": 35.349285,
      "lon": -80.6820039,
      "alt_m": 0.0
    },
    {
      "lat": 35.3492707,
      "lon": -80.6819951,
      "alt_m": 0.0
    },
    {
      "lat": 35.3492561,
      "lon": -80.6819871,
      "alt_m": 0.0
    },
    {
      "lat": 35.3492411,
      "lon": -80.6819801,
      "alt_m": 0.0
    },
    {
      "lat": 35.3492258,
      "lon": -80.6819743,
      "alt_m": 0.0
    },
    {
      "lat": 35.3492104,
      "lon": -80.6819692,
      "alt_m": 0.0
    },
    {
      "lat": 35.3491948,
      "lon": -80.6819649,
      "alt_m": 0.0
    },
    {
      "lat": 35.3491789,
      "lon": -80.6819617,
      "alt_m": 0.0
    },
    {
      "lat": 35.3491629,
      "lon": -80.6819593,
      "alt_m": 0.0
    },
    {
      "lat": 35.3491468,
      "lon": -80.681958,
      "alt_m": 0.0
    },
    {
      "lat": 35.3491306,
      "lon": -80.6819576,
      "alt_m": 0.0
    },
    {
      "lat": 35.3491142,
      "lon": -80.681958,
      "alt_m": 0.0
    },
    {
      "lat": 35.3490976,
      "lon": -80.6819592,
      "alt_m": 0.0
    },
    {
      "lat": 35.3490809,
      "lon": -80.6819615,
      "alt_m": 0.0
    },
    {
      "lat": 35.3490644,
      "lon": -80.6819648,
      "alt_m": 0.0
    },
    {
      "lat": 35.3490479,
      "lon": -80.6819689,
      "alt_m": 0.0
    },
    {
      "lat": 35.3490313,
      "lon": -80.6819741,
      "alt_m": 0.0
    },
    {
      "lat": 35.3490151,
      "lon": -80.6819804,
      "alt_m": 0.0
    },
    {
      "lat": 35.3489989,
      "lon": -80.6819875,
      "alt_m": 0.0
    },
    {
      "lat": 35.3489825,
      "lon": -80.6819955,
      "alt_m": 0.0
    },
    {
      "lat": 35.3489665,
      "lon": -80.6820045,
      "alt_m": 0.0
    },
    {
      "lat": 35.3489504,
      "lon": -80.6820143,
      "alt_m": 0.0
    },
    {
      "lat": 35.3489346,
      "lon": -80.682025,
      "alt_m": 0.0
    },
    {
      "lat": 35.348919,
      "lon": -80.6820365,
      "alt_m": 0.0
    },
    {
      "lat": 35.3489035,
      "lon": -80.6820489,
      "alt_m": 0.0
    },
    {
      "lat": 35.3488883,
      "lon": -80.6820623,
      "alt_m": 0.0
    },
    {
      "lat": 35.3488731,
      "lon": -80.6820761,
      "alt_m": 0.0
    },
    {
      "lat": 35.3488582,
      "lon": -80.6820908,
      "alt_m": 0.0
    },
    {
      "lat": 35.3488436,
      "lon": -80.6821064,
      "alt_m": 0.0
    },
    {
      "lat": 35.3488293,
      "lon": -80.6821227,
      "alt_m": 0.0
    },
    {
      "lat": 35.3488155,
      "lon": -80.6821401,
      "alt_m": 0.0
    },
    {
      "lat": 35.348802,
      "lon": -80.6821581,
      "alt_m": 0.0
    },
    {
      "lat": 35.3487888,
      "lon": -80.6821769,
      "alt_m": 0.0
    },
    {
      "lat": 35.3487759,
      "lon": -80.6821966,
      "alt_m": 0.0
    },
    {
      "lat": 35.3487633,
      "lon": -80.6822173,
      "alt_m": 0.0
    },
    {
      "lat": 35.3487511,
      "lon": -80.6822386,
      "alt_m": 0.0
    },
    {
      "lat": 35.3487391,
      "lon": -80.6822605,
      "alt_m": 0.0
    },
    {
      "lat": 35.3487274,
      "lon": -80.6822828,
      "alt_m": 0.0
    },
    {
      "lat": 35.3487161,
      "lon": -80.6823059,
      "alt_m": 0.0
    },
    {
      "lat": 35.3487052,
      "lon": -80.6823298,
      "alt_m": 0.0
    },
    {
      "lat": 35.3486946,
      "lon": -80.6823542,
      "alt_m": 0.0
    },
    {
      "lat": 35.3486843,
      "lon": -80.6823791,
      "alt_m": 0.0
    },
    {
      "lat": 35.3486741,
      "lon": -80.6824046,
      "alt_m": 0.0
    },
    {
      "lat": 35.3486641,
      "lon": -80.6824305,
      "alt_m": 0.0
    },
    {
      "lat": 35.3486544,
      "lon": -80.6824571,
      "alt_m": 0.0
    },
    {
      "lat": 35.348645,
      "lon": -80.682484,
      "alt_m": 0.0
    },
    {
      "lat": 35.3486358,
      "lon": -80.6825116,
      "alt_m": 0.0
    },
    {
      "lat": 35.3486268,
      "lon": -80.6825393,
      "alt_m": 0.0
    },
    {
      "lat": 35.3486179,
      "lon": -80.6825678,
      "alt_m": 0.0
    },
    {
      "lat": 35.3486091,
      "lon": -80.6825968,
      "alt_m": 0.0
    },
    {
      "lat": 35.3486005,
      "lon": -80.6826264,
      "alt_m": 0.0
    },
    {
      "lat": 35.3485921,
      "lon": -80.6826562,
      "alt_m": 0.0
    },
    {
      "lat": 35.3485839,
      "lon": -80.6826865,
      "alt_m": 0.0
    },
    {
      "lat": 35.3485759,
      "lon": -80.682717,
      "alt_m": 0.0
    },
    {
      "lat": 35.3485683,
      "lon": -80.6827472,
      "alt_m": 0.0
    },
    {
      "lat": 35.3485612,
      "lon": -80.6827773,
      "alt_m": 0.0
    },
    {
      "lat": 35.3485547,
      "lon": -80.682807,
      "alt_m": 0.0
    },
    {
      "lat": 35.3485488,
      "lon": -80.6828364,
      "alt_m": 0.0
    },
    {
      "lat": 35.3485434,
      "lon": -80.6828656,
      "alt_m": 0.0
    },
    {
      "lat": 35.3485389,
      "lon": -80.6828944,
      "alt_m": 0.0
    },
    {
      "lat": 35.3485349,
      "lon": -80.6829227,
      "alt_m": 0.0
    },
    {
      "lat": 35.3485315,
      "lon": -80.6829508,
      "alt_m": 0.0
    },
    {
      "lat": 35.3485289,
      "lon": -80.682979,
      "alt_m": 0.0
    },
    {
      "lat": 35.348527,
      "lon": -80.683007,
      "alt_m": 0.0
    },
    {
      "lat": 35.3485259,
      "lon": -80.6830348,
      "alt_m": 0.0
    },
    {
      "lat": 35.3485259,
      "lon": -80.6830628,
      "alt_m": 0.0
    },
    {
      "lat": 35.3485267,
      "lon": -80.6830904,
      "alt_m": 0.0
    },
    {
      "lat": 35.3485284,
      "lon": -80.6831177,
      "alt_m": 0.0
    },
    {
      "lat": 35.3485309,
      "lon": -80.6831447,
      "alt_m": 0.0
    },
    {
      "lat": 35.3485342,
      "lon": -80.6831714,
      "alt_m": 0.0
    },
    {
      "lat": 35.3485386,
      "lon": -80.6831978,
      "alt_m": 0.0
    },
    {
      "lat": 35.3485439,
      "lon": -80.6832239,
      "alt_m": 0.0
    },
    {
      "lat": 35.34855,
      "lon": -80.6832496,
      "alt_m": 0.0
    },
    {
      "lat": 35.348557,
      "lon": -80.6832747,
      "alt_m": 0.0
    },
    {
      "lat": 35.3485649,
      "lon": -80.6832993,
      "alt_m": 0.0
    },
    {
      "lat": 35.3485733,
      "lon": -80.6833233,
      "alt_m": 0.0
    },
    {
      "lat": 35.3485826,
      "lon": -80.6833467,
      "alt_m": 0.0
    },
    {
      "lat": 35.3485925,
      "lon": -80.6833694,
      "alt_m": 0.0
    },
    {
      "lat": 35.3486034,
      "lon": -80.6833913,
      "alt_m": 0.0
    },
    {
      "lat": 35.348615,
      "lon": -80.6834127,
      "alt_m": 0.0
    },
    {
      "lat": 35.3486273,
      "lon": -80.6834335,
      "alt_m": 0.0
    },
    {
      "lat": 35.3486402,
      "lon": -80.6834539,
      "alt_m": 0.0
    },
    {
      "lat": 35.3486535,
      "lon": -80.6834735,
      "alt_m": 0.0
    },
    {
      "lat": 35.3486675,
      "lon": -80.6834926,
      "alt_m": 0.0
    },
    {
      "lat": 35.3486821,
      "lon": -80.6835111,
      "alt_m": 0.0
    },
    {
      "lat": 35.3486973,
      "lon": -80.6835292,
      "alt_m": 0.0
    },
    {
      "lat": 35.3487129,
      "lon": -80.6835469,
      "alt_m": 0.0
    },
    {
      "lat": 35.3487293,
      "lon": -80.6835639,
      "alt_m": 0.0
    },
    {
      "lat": 35.3487463,
      "lon": -80.6835801,
      "alt_m": 0.0
    },
    {
      "lat": 35.3487637,
      "lon": -80.6835956,
      "alt_m": 0.0
    },
    {
      "lat": 35.3487816,
      "lon": -80.6836104,
      "alt_m": 0.0
    },
    {
      "lat": 35.3487998,
      "lon": -80.6836245,
      "alt_m": 0.0
    },
    {
      "lat": 35.3488187,
      "lon": -80.6836379,
      "alt_m": 0.0
    },
    {
      "lat": 35.3488379,
      "lon": -80.6836505,
      "alt_m": 0.0
    },
    {
      "lat": 35.3488577,
      "lon": -80.6836622,
      "alt_m": 0.0
    },
    {
      "lat": 35.3488779,
      "lon": -80.6836728,
      "alt_m": 0.0
    },
    {
      "lat": 35.3488984,
      "lon": -80.6836826,
      "alt_m": 0.0
    },
    {
      "lat": 35.3489191,
      "lon": -80.6836916,
      "alt_m": 0.0
    },
    {
      "lat": 35.3489402,
      "lon": -80.6837001,
      "alt_m": 0.0
    },
    {
      "lat": 35.3489617,
      "lon": -80.6837078,
      "alt_m": 0.0
    },
    {
      "lat": 35.3489835,
      "lon": -80.6837148,
      "alt_m": 0.0
    },
    {
      "lat": 35.3490055,
      "lon": -80.6837213,
      "alt_m": 0.0
    },
    {
      "lat": 35.3490278,
      "lon": -80.683727,
      "alt_m": 0.0
    },
    {
      "lat": 35.3490505,
      "lon": -80.6837322,
      "alt_m": 0.0
    },
    {
      "lat": 35.3490735,
      "lon": -80.6837368,
      "alt_m": 0.0
    },
    {
      "lat": 35.3490969,
      "lon": -80.683741,
      "alt_m": 0.0
    },
    {
      "lat": 35.3491207,
      "lon": -80.6837451,
      "alt_m": 0.0
    },
    {
      "lat": 35.3491447,
      "lon": -80.683749,
      "alt_m": 0.0
    },
    {
      "lat": 35.349169,
      "lon": -80.6837528,
      "alt_m": 0.0
    },
    {
      "lat": 35.3491937,
      "lon": -80.6837567,
      "alt_m": 0.0
    },
    {
      "lat": 35.3492188,
      "lon": -80.6837607,
      "alt_m": 0.0
    },
    {
      "lat": 35.3492442,
      "lon": -80.6837649,
      "alt_m": 0.0
    },
    {
      "lat": 35.3492699,
      "lon": -80.6837693,
      "alt_m": 0.0
    },
    {
      "lat": 35.3492959,
      "lon": -80.6837741,
      "alt_m": 0.0
    },
    {
      "lat": 35.349322,
      "lon": -80.6837789,
      "alt_m": 0.0
    },
    {
      "lat": 35.3493486,
      "lon": -80.6837842,
      "alt_m": 0.0
    },
    {
      "lat": 35.3493755,
      "lon": -80.6837899,
      "alt_m": 0.0
    },
    {
      "lat": 35.3494023,
      "lon": -80.6837961,
      "alt_m": 0.0
    },
    {
      "lat": 35.3494287,
      "lon": -80.6838025,
      "alt_m": 0.0
    },
    {
      "lat": 35.3494543,
      "lon": -80.683809,
      "alt_m": 0.0
    },
    {
      "lat": 35.3494791,
      "lon": -80.6838159,
      "alt_m": 0.0
    },
    {
      "lat": 35.3495033,
      "lon": -80.6838232,
      "alt_m": 0.0
    },
    {
      "lat": 35.3495268,
      "lon": -80.6838309,
      "alt_m": 0.0
    },
    {
      "lat": 35.3495495,
      "lon": -80.6838391,
      "alt_m": 0.0
    },
    {
      "lat": 35.3495714,
      "lon": -80.683848,
      "alt_m": 0.0
    },
    {
      "lat": 35.3495927,
      "lon": -80.6838572,
      "alt_m": 0.0
    },
    {
      "lat": 35.3496132,
      "lon": -80.6838669,
      "alt_m": 0.0
    },
    {
      "lat": 35.3496329,
      "lon": -80.6838769,
      "alt_m": 0.0
    },
    {
      "lat": 35.3496517,
      "lon": -80.6838874,
      "alt_m": 0.0
    },
    {
      "lat": 35.3496697,
      "lon": -80.6838986,
      "alt_m": 0.0
    },
    {
      "lat": 35.3496867,
      "lon": -80.6839101,
      "alt_m": 0.0
    },
    {
      "lat": 35.3497029,
      "lon": -80.6839225,
      "alt_m": 0.0
    },
    {
      "lat": 35.3497184,
      "lon": -80.6839353,
      "alt_m": 0.0
    },
    {
      "lat": 35.3497331,
      "lon": -80.6839488,
      "alt_m": 0.0
    },
    {
      "lat": 35.3497468,
      "lon": -80.6839629,
      "alt_m": 0.0
    },
    {
      "lat": 35.3497594,
      "lon": -80.6839774,
      "alt_m": 0.0
    },
    {
      "lat": 35.3497714,
      "lon": -80.6839927,
      "alt_m": 0.0
    },
    {
      "lat": 35.3497826,
      "lon": -80.6840088,
      "alt_m": 0.0
    },
    {
      "lat": 35.3497931,
      "lon": -80.6840252,
      "alt_m": 0.0
    },
    {
      "lat": 35.349803,
      "lon": -80.6840423,
      "alt_m": 0.0
    },
    {
      "lat": 35.3498119,
      "lon": -80.6840597,
      "alt_m": 0.0
    },
    {
      "lat": 35.3498202,
      "lon": -80.684078,
      "alt_m": 0.0
    },
    {
      "lat": 35.3498279,
      "lon": -80.6840967,
      "alt_m": 0.0
    },
    {
      "lat": 35.3498348,
      "lon": -80.6841158,
      "alt_m": 0.0
    },
    {
      "lat": 35.3498409,
      "lon": -80.6841352,
      "alt_m": 0.0
    },
    {
      "lat": 35.3498464,
      "lon": -80.6841548,
      "alt_m": 0.0
    },
    {
      "lat": 35.349851,
      "lon": -80.6841747,
      "alt_m": 0.0
    },
    {
      "lat": 35.3498547,
      "lon": -80.6841951,
      "alt_m": 0.0
    },
    {
      "lat": 35.3498577,
      "lon": -80.6842157,
      "alt_m": 0.0
    },
    {
      "lat": 35.3498598,
      "lon": -80.6842367,
      "alt_m": 0.0
    },
    {
      "lat": 35.349861,
      "lon": -80.684258,
      "alt_m": 0.0
    },
    {
      "lat": 35.3498614,
      "lon": -80.6842794,
      "alt_m": 0.0
    },
    {
      "lat": 35.3498609,
      "lon": -80.6843008,
      "alt_m": 0.0
    },
    {
      "lat": 35.3498595,
      "lon": -80.6843222,
      "alt_m": 0.0
    },
    {
      "lat": 35.3498572,
      "lon": -80.6843433,
      "alt_m": 0.0
    },
    {
      "lat": 35.349854,
      "lon": -80.6843645,
      "alt_m": 0.0
    },
    {
      "lat": 35.34985,
      "lon": -80.6843853,
      "alt_m": 0.0
    },
    {
      "lat": 35.3498449,
      "lon": -80.684406,
      "alt_m": 0.0
    },
    {
      "lat": 35.349839,
      "lon": -80.6844262,
      "alt_m": 0.0
    },
    {
      "lat": 35.3498323,
      "lon": -80.684446,
      "alt_m": 0.0
    },
    {
      "lat": 35.3498247,
      "lon": -80.6844651,
      "alt_m": 0.0
    },
    {
      "lat": 35.3498162,
      "lon": -80.6844839,
      "alt_m": 0.0
    },
    {
      "lat": 35.3498069,
      "lon": -80.6845018,
      "alt_m": 0.0
    },
    {
      "lat": 35.3497968,
      "lon": -80.6845194,
      "alt_m": 0.0
    },
    {
      "lat": 35.3497861,
      "lon": -80.6845365,
      "alt_m": 0.0
    },
    {
      "lat": 35.3497748,
      "lon": -80.6845526,
      "alt_m": 0.0
    },
    {
      "lat": 35.3497625,
      "lon": -80.6845683,
      "alt_m": 0.0
    },
    {
      "lat": 35.3497497,
      "lon": -80.6845832,
      "alt_m": 0.0
    },
    {
      "lat": 35.3497362,
      "lon": -80.6845976,
      "alt_m": 0.0
    },
    {
      "lat": 35.3497222,
      "lon": -80.6846115,
      "alt_m": 0.0
    },
    {
      "lat": 35.3497075,
      "lon": -80.6846246,
      "alt_m": 0.0
    },
    {
      "lat": 35.3496921,
      "lon": -80.684637,
      "alt_m": 0.0
    },
    {
      "lat": 35.3496765,
      "lon": -80.6846487,
      "alt_m": 0.0
    },
    {
      "lat": 35.3496601,
      "lon": -80.6846595,
      "alt_m": 0.0
    },
    {
      "lat": 35.3496432,
      "lon": -80.6846695,
      "alt_m": 0.0
    },
    {
      "lat": 35.3496258,
      "lon": -80.6846789,
      "alt_m": 0.0
    },
    {
      "lat": 35.3496079,
      "lon": -80.6846873,
      "alt_m": 0.0
    },
    {
      "lat": 35.34959,
      "lon": -80.6846948,
      "alt_m": 0.0
    },
    {
      "lat": 35.3495716,
      "lon": -80.6847014,
      "alt_m": 0.0
    },
    {
      "lat": 35.3495527,
      "lon": -80.6847069,
      "alt_m": 0.0
    },
    {
      "lat": 35.3495337,
      "lon": -80.6847113,
      "alt_m": 0.0
    },
    {
      "lat": 35.3495146,
      "lon": -80.6847147,
      "alt_m": 0.0
    },
    {
      "lat": 35.3494952,
      "lon": -80.6847171,
      "alt_m": 0.0
    },
    {
      "lat": 35.3494757,
      "lon": -80.6847182,
      "alt_m": 0.0
    },
    {
      "lat": 35.3494563,
      "lon": -80.6847183,
      "alt_m": 0.0
    },
    {
      "lat": 35.3494366,
      "lon": -80.6847175,
      "alt_m": 0.0
    },
    {
      "lat": 35.3494166,
      "lon": -80.6847156,
      "alt_m": 0.0
    },
    {
      "lat": 35.3493965,
      "lon": -80.6847125,
      "alt_m": 0.0
    },
    {
      "lat": 35.3493763,
      "lon": -80.6847085,
      "alt_m": 0.0
    },
    {
      "lat": 35.3493564,
      "lon": -80.6847035,
      "alt_m": 0.0
    },
    {
      "lat": 35.3493365,
      "lon": -80.6846976,
      "alt_m": 0.0
    },
    {
      "lat": 35.3493168,
      "lon": -80.6846907,
      "alt_m": 0.0
    },
    {
      "lat": 35.3492971,
      "lon": -80.6846827,
      "alt_m": 0.0
    },
    {
      "lat": 35.3492776,
      "lon": -80.6846736,
      "alt_m": 0.0
    },
    {
      "lat": 35.3492583,
      "lon": -80.6846635,
      "alt_m": 0.0
    },
    {
      "lat": 35.3492392,
      "lon": -80.6846525,
      "alt_m": 0.0
    },
    {
      "lat": 35.3492203,
      "lon": -80.6846407,
      "alt_m": 0.0
    },
    {
      "lat": 35.3492015,
      "lon": -80.6846279,
      "alt_m": 0.0
    },
    {
      "lat": 35.349183,
      "lon": -80.6846145,
      "alt_m": 0.0
    },
    {
      "lat": 35.3491645,
      "lon": -80.6846003,
      "alt_m": 0.0
    },
    {
      "lat": 35.3491457,
      "lon": -80.6845855,
      "alt_m": 0.0
    },
    {
      "lat": 35.349127,
      "lon": -80.6845702,
      "alt_m": 0.0
    },
    {
      "lat": 35.3491083,
      "lon": -80.6845543,
      "alt_m": 0.0
    },
    {
      "lat": 35.3490893,
      "lon": -80.6845378,
      "alt_m": 0.0
    },
    {
      "lat": 35.3490702,
      "lon": -80.6845209,
      "alt_m": 0.0
    },
    {
      "lat": 35.3490509,
      "lon": -80.6845035,
      "alt_m": 0.0
    },
    {
      "lat": 35.3490315,
      "lon": -80.6844857,
      "alt_m": 0.0
    },
    {
      "lat": 35.349012,
      "lon": -80.6844674,
      "alt_m": 0.0
    },
    {
      "lat": 35.3489925,
      "lon": -80.6844487,
      "alt_m": 0.0
    },
    {
      "lat": 35.3489731,
      "lon": -80.6844299,
      "alt_m": 0.0
    },
    {
      "lat": 35.348954,
      "lon": -80.684411,
      "alt_m": 0.0
    },
    {
      "lat": 35.3489354,
      "lon": -80.6843923,
      "alt_m": 0.0
    },
    {
      "lat": 35.3489172,
      "lon": -80.6843742,
      "alt_m": 0.0
    },
    {
      "lat": 35.3488995,
      "lon": -80.6843566,
      "alt_m": 0.0
    },
    {
      "lat": 35.3488823,
      "lon": -80.6843396,
      "alt_m": 0.0
    },
    {
      "lat": 35.3488655,
      "lon": -80.6843231,
      "alt_m": 0.0
    },
    {
      "lat": 35.3488491,
      "lon": -80.6843071,
      "alt_m": 0.0
    },
    {
      "lat": 35.348833,
      "lon": -80.6842916,
      "alt_m": 0.0
    },
    {
      "lat": 35.3488172,
      "lon": -80.6842768,
      "alt_m": 0.0
    },
    {
      "lat": 35.3488017,
      "lon": -80.6842629,
      "alt_m": 0.0
    },
    {
      "lat": 35.3487862,
      "lon": -80.6842498,
      "alt_m": 0.0
    },
    {
      "lat": 35.3487709,
      "lon": -80.6842373,
      "alt_m": 0.0
    },
    {
      "lat": 35.3487557,
      "lon": -80.6842258,
      "alt_m": 0.0
    },
    {
      "lat": 35.3487406,
      "lon": -80.6842154,
      "alt_m": 0.0
    },
    {
      "lat": 35.3487255,
      "lon": -80.6842058,
      "alt_m": 0.0
    },
    {
      "lat": 35.3487102,
      "lon": -80.6841973,
      "alt_m": 0.0
    },
    {
      "lat": 35.348695,
      "lon": -80.6841898,
      "alt_m": 0.0
    },
    {
      "lat": 35.3486798,
      "lon": -80.6841834,
      "alt_m": 0.0
    },
    {
      "lat": 35.3486642,
      "lon": -80.684178,
      "alt_m": 0.0
    },
    {
      "lat": 35.3486485,
      "lon": -80.6841735,
      "alt_m": 0.0
    },
    {
      "lat": 35.3486327,
      "lon": -80.6841702,
      "alt_m": 0.0
    },
    {
      "lat": 35.3486168,
      "lon": -80.684168,
      "alt_m": 0.0
    },
    {
      "lat": 35.3486011,
      "lon": -80.6841671,
      "alt_m": 0.0
    },
    {
      "lat": 35.3485855,
      "lon": -80.6841671,
      "alt_m": 0.0
    },
    {
      "lat": 35.3485699,
      "lon": -80.6841683,
      "alt_m": 0.0
    },
    {
      "lat": 35.3485545,
      "lon": -80.6841705,
      "alt_m": 0.0
    },
    {
      "lat": 35.3485396,
      "lon": -80.6841739,
      "alt_m": 0.0
    },
    {
      "lat": 35.3485249,
      "lon": -80.6841784,
      "alt_m": 0.0
    },
    {
      "lat": 35.3485107,
      "lon": -80.6841839,
      "alt_m": 0.0
    },
    {
      "lat": 35.3484968,
      "lon": -80.6841904,
      "alt_m": 0.0
    },
    {
      "lat": 35.3484831,
      "lon": -80.6841979,
      "alt_m": 0.0
    },
    {
      "lat": 35.3484702,
      "lon": -80.6842064,
      "alt_m": 0.0
    },
    {
      "lat": 35.3484578,
      "lon": -80.684216,
      "alt_m": 0.0
    },
    {
      "lat": 35.3484458,
      "lon": -80.6842265,
      "alt_m": 0.0
    },
    {
      "lat": 35.3484342,
      "lon": -80.6842375,
      "alt_m": 0.0
    },
    {
      "lat": 35.3484228,
      "lon": -80.6842494,
      "alt_m": 0.0
    },
    {
      "lat": 35.3484118,
      "lon": -80.6842621,
      "alt_m": 0.0
    },
    {
      "lat": 35.3484016,
      "lon": -80.6842754,
      "alt_m": 0.0
    },
    {
      "lat": 35.3483919,
      "lon": -80.6842897,
      "alt_m": 0.0
    },
    {
      "lat": 35.3483829,
      "lon": -80.6843047,
      "alt_m": 0.0
    },
    {
      "lat": 35.3483744,
      "lon": -80.6843202,
      "alt_m": 0.0
    },
    {
      "lat": 35.3483665,
      "lon": -80.6843362,
      "alt_m": 0.0
    },
    {
      "lat": 35.3483594,
      "lon": -80.684353,
      "alt_m": 0.0
    },
    {
      "lat": 35.3483529,
      "lon": -80.6843702,
      "alt_m": 0.0
    },
    {
      "lat": 35.3483473,
      "lon": -80.6843881,
      "alt_m": 0.0
    },
    {
      "lat": 35.3483424,
      "lon": -80.6844064,
      "alt_m": 0.0
    },
    {
      "lat": 35.3483383,
      "lon": -80.684425,
      "alt_m": 0.0
    },
    {
      "lat": 35.3483348,
      "lon": -80.684444,
      "alt_m": 0.0
    },
    {
      "lat": 35.3483319,
      "lon": -80.6844631,
      "alt_m": 0.0
    },
    {
      "lat": 35.3483297,
      "lon": -80.6844826,
      "alt_m": 0.0
    },
    {
      "lat": 35.3483284,
      "lon": -80.6845024,
      "alt_m": 0.0
    },
    {
      "lat": 35.3483275,
      "lon": -80.6845225,
      "alt_m": 0.0
    },
    {
      "lat": 35.3483275,
      "lon": -80.6845427,
      "alt_m": 0.0
    },
    {
      "lat": 35.3483282,
      "lon": -80.684563,
      "alt_m": 0.0
    },
    {
      "lat": 35.3483297,
      "lon": -80.6845834,
      "alt_m": 0.0
    },
    {
      "lat": 35.3483318,
      "lon": -80.6846042,
      "alt_m": 0.0
    },
    {
      "lat": 35.3483348,
      "lon": -80.684625,
      "alt_m": 0.0
    },
    {
      "lat": 35.3483384,
      "lon": -80.6846457,
      "alt_m": 0.0
    },
    {
      "lat": 35.3483428,
      "lon": -80.6846664,
      "alt_m": 0.0
    },
    {
      "lat": 35.3483483,
      "lon": -80.684687,
      "alt_m": 0.0
    },
    {
      "lat": 35.3483544,
      "lon": -80.6847075,
      "alt_m": 0.0
    },
    {
      "lat": 35.3483612,
      "lon": -80.6847277,
      "alt_m": 0.0
    },
    {
      "lat": 35.3483687,
      "lon": -80.6847478,
      "alt_m": 0.0
    },
    {
      "lat": 35.348377,
      "lon": -80.6847678,
      "alt_m": 0.0
    },
    {
      "lat": 35.3483861,
      "lon": -80.6847875,
      "alt_m": 0.0
    },
    {
      "lat": 35.3483958,
      "lon": -80.6848069,
      "alt_m": 0.0
    },
    {
      "lat": 35.3484063,
      "lon": -80.684826,
      "alt_m": 0.0
    },
    {
      "lat": 35.3484173,
      "lon": -80.6848447,
      "alt_m": 0.0
    },
    {
      "lat": 35.348429,
      "lon": -80.6848634,
      "alt_m": 0.0
    },
    {
      "lat": 35.3484412,
      "lon": -80.6848816,
      "alt_m": 0.0
    },
    {
      "lat": 35.3484543,
      "lon": -80.6848995,
      "alt_m": 0.0
    },
    {
      "lat": 35.3484679,
      "lon": -80.6849167,
      "alt_m": 0.0
    },
    {
      "lat": 35.3484822,
      "lon": -80.6849338,
      "alt_m": 0.0
    },
    {
      "lat": 35.3484968,
      "lon": -80.6849507,
      "alt_m": 0.0
    },
    {
      "lat": 35.3485122,
      "lon": -80.6849671,
      "alt_m": 0.0
    },
    {
      "lat": 35.3485282,
      "lon": -80.6849831,
      "alt_m": 0.0
    },
    {
      "lat": 35.3485447,
      "lon": -80.6849986,
      "alt_m": 0.0
    },
    {
      "lat": 35.3485617,
      "lon": -80.6850138,
      "alt_m": 0.0
    },
    {
      "lat": 35.3485794,
      "lon": -80.6850286,
      "alt_m": 0.0
    },
    {
      "lat": 35.3485976,
      "lon": -80.6850428,
      "alt_m": 0.0
    },
    {
      "lat": 35.3486165,
      "lon": -80.6850567,
      "alt_m": 0.0
    },
    {
      "lat": 35.3486358,
      "lon": -80.68507,
      "alt_m": 0.0
    },
    {
      "lat": 35.3486557,
      "lon": -80.685083,
      "alt_m": 0.0
    },
    {
      "lat": 35.3486762,
      "lon": -80.6850955,
      "alt_m": 0.0
    },
    {
      "lat": 35.3486971,
      "lon": -80.6851073,
      "alt_m": 0.0
    },
    {
      "lat": 35.3487186,
      "lon": -80.6851183,
      "alt_m": 0.0
    },
    {
      "lat": 35.3487406,
      "lon": -80.685129,
      "alt_m": 0.0
    },
    {
      "lat": 35.348763,
      "lon": -80.6851393,
      "alt_m": 0.0
    },
    {
      "lat": 35.3487858,
      "lon": -80.6851494,
      "alt_m": 0.0
    },
    {
      "lat": 35.3488091,
      "lon": -80.6851589,
      "alt_m": 0.0
    },
    {
      "lat": 35.3488328,
      "lon": -80.6851677,
      "alt_m": 0.0
    },
    {
      "lat": 35.3488571,
      "lon": -80.6851761,
      "alt_m": 0.0
    },
    {
      "lat": 35.3488818,
      "lon": -80.6851839,
      "alt_m": 0.0
    },
    {
      "lat": 35.3489069,
      "lon": -80.6851915,
      "alt_m": 0.0
    },
    {
      "lat": 35.3489324,
      "lon": -80.6851988,
      "alt_m": 0.0
    },
    {
      "lat": 35.3489582,
      "lon": -80.6852055,
      "alt_m": 0.0
    },
    {
      "lat": 35.3489845,
      "lon": -80.6852117,
      "alt_m": 0.0
    },
    {
      "lat": 35.3490111,
      "lon": -80.6852172,
      "alt_m": 0.0
    },
    {
      "lat": 35.349038,
      "lon": -80.6852225,
      "alt_m": 0.0
    },
    {
      "lat": 35.3490648,
      "lon": -80.6852271,
      "alt_m": 0.0
    },
    {
      "lat": 35.3490913,
      "lon": -80.6852317,
      "alt_m": 0.0
    },
    {
      "lat": 35.3491173,
      "lon": -80.6852359,
      "alt_m": 0.0
    },
    {
      "lat": 35.3491426,
      "lon": -80.6852399,
      "alt_m": 0.0
    },
    {
      "lat": 35.3491673,
      "lon": -80.6852433,
      "alt_m": 0.0
    },
    {
      "lat": 35.3491912,
      "lon": -80.6852465,
      "alt_m": 0.0
    },
    {
      "lat": 35.3492145,
      "lon": -80.6852495,
      "alt_m": 0.0
    },
    {
      "lat": 35.3492368,
      "lon": -80.685252,
      "alt_m": 0.0
    },
    {
      "lat": 35.3492586,
      "lon": -80.6852543,
      "alt_m": 0.0
    },
    {
      "lat": 35.3492796,
      "lon": -80.6852562,
      "alt_m": 0.0
    },
    {
      "lat": 35.3492998,
      "lon": -80.685258,
      "alt_m": 0.0
    },
    {
      "lat": 35.3493195,
      "lon": -80.6852597,
      "alt_m": 0.0
    },
    {
      "lat": 35.3493387,
      "lon": -80.6852616,
      "alt_m": 0.0
    },
    {
      "lat": 35.3493572,
      "lon": -80.6852636,
      "alt_m": 0.0
    },
    {
      "lat": 35.3493752,
      "lon": -80.6852655,
      "alt_m": 0.0
    },
    {
      "lat": 35.3493927,
      "lon": -80.6852676,
      "alt_m": 0.0
    },
    {
      "lat": 35.3494098,
      "lon": -80.68527,
      "alt_m": 0.0
    },
    {
      "lat": 35.3495787,
      "lon": -80.6852716,
      "alt_m": 0.0
    },
    {
      "lat": 35.3497396,
      "lon": -80.6852704,
      "alt_m": 0.0
    },
    {
      "lat": 35.3498045,
      "lon": -80.6852638,
      "alt_m": 0.0
    },
    {
      "lat": 35.3498602,
      "lon": -80.6852458,
      "alt_m": 0.0
    },
    {
      "lat": 35.3499148,
      "lon": -80.6852127,
      "alt_m": 0.0
    },
    {
      "lat": 35.3499697,
      "lon": -80.685162,
      "alt_m": 0.0
    },
    {
      "lat": 35.3500324,
      "lon": -80.6850958,
      "alt_m": 0.0
    },
    {
      "lat": 35.3500739,
      "lon": -80.68504,
      "alt_m": 0.0
    },
    {
      "lat": 35.3501026,
      "lon": -80.6849835,
      "alt_m": 0.0
    },
    {
      "lat": 35.350122,
      "lon": -80.6849253,
      "alt_m": 0.0
    },
    {
      "lat": 35.3501341,
      "lon": -80.6848472,
      "alt_m": 0.0
    },
    {
      "lat": 35.3501397,
      "lon": -80.6847535,
      "alt_m": 0.0
    },
    {
      "lat": 35.3501443,
      "lon": -80.6842472,
      "alt_m": 0.0
    },
    {
      "lat": 35.3501506,
      "lon": -80.6841787,
      "alt_m": 0.0
    },
    {
      "lat": 35.3501597,
      "lon": -80.6841036,
      "alt_m": 0.0
    },
    {
      "lat": 35.3501756,
      "lon": -80.6840267,
      "alt_m": 0.0
    },
    {
      "lat": 35.3501987,
      "lon": -80.6839499,
      "alt_m": 0.0
    },
    {
      "lat": 35.3502323,
      "lon": -80.683881,
      "alt_m": 0.0
    },
    {
      "lat": 35.3502781,
      "lon": -80.6838109,
      "alt_m": 0.0
    },
    {
      "lat": 35.3503344,
      "lon": -80.6837488,
      "alt_m": 0.0
    },
    {
      "lat": 35.3504008,
      "lon": -80.6836926,
      "alt_m": 0.0
    },
    {
      "lat": 35.3504953,
      "lon": -80.6836241,
      "alt_m": 0.0
    },
    {
      "lat": 35.3508793,
      "lon": -80.683371,
      "alt_m": 0.0
    },
    {
      "lat": 35.3509064,
      "lon": -80.6833532,
      "alt_m": 0.0
    },
    {
      "lat": 35.3509338,
      "lon": -80.6833354,
      "alt_m": 0.0
    },
    {
      "lat": 35.3509617,
      "lon": -80.6833177,
      "alt_m": 0.0
    },
    {
      "lat": 35.35099,
      "lon": -80.6833002,
      "alt_m": 0.0
    },
    {
      "lat": 35.3510188,
      "lon": -80.683283,
      "alt_m": 0.0
    },
    {
      "lat": 35.351048,
      "lon": -80.6832657,
      "alt_m": 0.0
    },
    {
      "lat": 35.3510772,
      "lon": -80.6832484,
      "alt_m": 0.0
    },
    {
      "lat": 35.3511064,
      "lon": -80.6832314,
      "alt_m": 0.0
    },
    {
      "lat": 35.3511353,
      "lon": -80.6832145,
      "alt_m": 0.0
    },
    {
      "lat": 35.3511638,
      "lon": -80.6831977,
      "alt_m": 0.0
    },
    {
      "lat": 35.351192,
      "lon": -80.6831812,
      "alt_m": 0.0
    },
    {
      "lat": 35.3512197,
      "lon": -80.6831647,
      "alt_m": 0.0
    },
    {
      "lat": 35.351247,
      "lon": -80.6831483,
      "alt_m": 0.0
    },
    {
      "lat": 35.3512739,
      "lon": -80.6831321,
      "alt_m": 0.0
    },
    {
      "lat": 35.3513004,
      "lon": -80.683116,
      "alt_m": 0.0
    },
    {
      "lat": 35.3513265,
      "lon": -80.6830998,
      "alt_m": 0.0
    },
    {
      "lat": 35.3513521,
      "lon": -80.6830837,
      "alt_m": 0.0
    },
    {
      "lat": 35.3513773,
      "lon": -80.6830676,
      "alt_m": 0.0
    },
    {
      "lat": 35.3514019,
      "lon": -80.6830511,
      "alt_m": 0.0
    },
    {
      "lat": 35.3514261,
      "lon": -80.6830345,
      "alt_m": 0.0
    },
    {
      "lat": 35.35145,
      "lon": -80.6830174,
      "alt_m": 0.0
    },
    {
      "lat": 35.3514734,
      "lon": -80.6829999,
      "alt_m": 0.0
    },
    {
      "lat": 35.3514964,
      "lon": -80.6829821,
      "alt_m": 0.0
    },
    {
      "lat": 35.3515188,
      "lon": -80.682964,
      "alt_m": 0.0
    },
    {
      "lat": 35.3515406,
      "lon": -80.6829455,
      "alt_m": 0.0
    },
    {
      "lat": 35.3515618,
      "lon": -80.6829266,
      "alt_m": 0.0
    },
    {
      "lat": 35.3515825,
      "lon": -80.6829073,
      "alt_m": 0.0
    },
    {
      "lat": 35.351603,
      "lon": -80.6828876,
      "alt_m": 0.0
    },
    {
      "lat": 35.3516229,
      "lon": -80.6828676,
      "alt_m": 0.0
    },
    {
      "lat": 35.3516423,
      "lon": -80.6828476,
      "alt_m": 0.0
    },
    {
      "lat": 35.3516615,
      "lon": -80.6828275,
      "alt_m": 0.0
    },
    {
      "lat": 35.35168,
      "lon": -80.6828062,
      "alt_m": 0.0
    },
    {
      "lat": 35.3516975,
      "lon": -80.6827837,
      "alt_m": 0.0
    },
    {
      "lat": 35.3517143,
      "lon": -80.6827609,
      "alt_m": 0.0
    },
    {
      "lat": 35.3517306,
      "lon": -80.6827374,
      "alt_m": 0.0
    },
    {
      "lat": 35.3517467,
      "lon": -80.6827135,
      "alt_m": 0.0
    },
    {
      "lat": 35.351762,
      "lon": -80.6826892,
      "alt_m": 0.0
    },
    {
      "lat": 35.3517761,
      "lon": -80.6826638,
      "alt_m": 0.0
    },
    {
      "lat": 35.3517894,
      "lon": -80.6826381,
      "alt_m": 0.0
    },
    {
      "lat": 35.3518024,
      "lon": -80.682612,
      "alt_m": 0.0
    },
    {
      "lat": 35.3518148,
      "lon": -80.6825856,
      "alt_m": 0.0
    },
    {
      "lat": 35.3518264,
      "lon": -80.6825588,
      "alt_m": 0.0
    },
    {
      "lat": 35.3518374,
      "lon": -80.6825315,
      "alt_m": 0.0
    },
    {
      "lat": 35.3518401,
      "lon": -80.6825241,
      "alt_m": 0.0
    }
  ]
}