{
  "source_file": "0sxccwgb.tkk",
  "full_name": "NAF Practice Track Molde",
  "name": "NAF Practice Track Molde",
  "venue_id": "0sxccwgb",
  "short_name": "Molde",
  "country": "NO",
  "track_length_m": 962.9,
  "reference_point": {
    "lat": 62.7980262,
    "lon": 7.2936195,
    "alt_m": 0.0
  },
  "start_finish": {
    "lat": 62.797492,
    "lon": 7.2939689
  },
  "surface": "asphalt",
  "timezone": "Europe/Oslo",
  "timezone_label": "(UTC+01:00) Amsterdam, Berlin, Bern, Rome, Stockholm, Vienna",
  "contact": {
    "city": "Fræna Municipality",
    "address": "Fv64",
    "postal_code": "6445",
    "phone": "+47 23 21 31 00",
    "url": "https://www.naf.no/her-finner-du-naf/naf-ovingsbaner/ovingsbane-molde/"
  },
  "start_finish_line": {
    "p1": {
      "lat": 62.7974412,
      "lon": 7.29399
    },
    "p2": {
      "lat": 62.7975428,
      "lon": 7.2939478
    }
  },
  "logo_file": "NAF Practice Track Molde_logo.png",
  "svg_file": "NAF Practice Track Molde.svg",
  "gps_points": [
    {
      "lat": 62.797492,
      "lon": 7.2939689,
      "alt_m": 0.0
    },
    {
      "lat": 62.7974285,
      "lon": 7.293237,
      "alt_m": -32768.0
    },
    {
      "lat": 62.797399,
      "lon": 7.2928614,
      "alt_m": -32768.0
    },
    {
      "lat": 62.7973947,
      "lon": 7.2927365,
      "alt_m": -32768.0
    },
    {
      "lat": 62.7973973,
      "lon": 7.2926113,
      "alt_m": -32768.0
    },
    {
      "lat": 62.797409,
      "lon": 7.2924917,
      "alt_m": -32768.0
    },
    {
      "lat": 62.7974284,
      "lon": 7.2923769,
      "alt_m": -32768.0
    },
    {
      "lat": 62.7974832,
      "lon": 7.2921595,
      "alt_m": -32768.0
    },
    {
      "lat": 62.7975514,
      "lon": 7.2919594,
      "alt_m": -32768.0
    },
    {
      "lat": 62.7975913,
      "lon": 7.2918663,
      "alt_m": -32768.0
    },
    {
      "lat": 62.7976338,
      "lon": 7.2917825,
      "alt_m": -32768.0
    },
    {
      "lat": 62.797681,
      "lon": 7.2917061,
      "alt_m": -32768.0
    },
    {
      "lat": 62.7977324,
      "lon": 7.2916462,
      "alt_m": -32768.0
    },
    {
      "lat": 62.7977866,
      "lon": 7.2916023,
      "alt_m": -32768.0
    },
    {
      "lat": 62.7978146,
      "lon": 7.2915893,
      "alt_m": -32768.0
    },
    {
      "lat": 62.7978428,
      "lon": 7.2915832,
      "alt_m": -32768.0
    },
    {
      "lat": 62.7978707,
      "lon": 7.2915854,
      "alt_m": -32768.0
    },
    {
      "lat": 62.7978983,
      "lon": 7.2915944,
      "alt_m": -32768.0
    },
    {
      "lat": 62.7979514,
      "lon": 7.2916298,
      "alt_m": -32768.0
    },
    {
      "lat": 62.7980027,
      "lon": 7.291682,
      "alt_m": -32768.0
    },
    {
      "lat": 62.7980507,
      "lon": 7.2917473,
      "alt_m": -32768.0
    },
    {
      "lat": 62.798094,
      "lon": 7.2918233,
      "alt_m": -32768.0
    },
    {
      "lat": 62.7981312,
      "lon": 7.2919107,
      "alt_m": -32768.0
    },
    {
      "lat": 62.7981628,
      "lon": 7.2920088,
      "alt_m": -32768.0
    },
    {
      "lat": 62.7981858,
      "lon": 7.2921131,
      "alt_m": -32768.0
    },
    {
      "lat": 62.7981945,
      "lon": 7.2921647,
      "alt_m": -32768.0
    },
    {
      "lat": 62.7982075,
      "lon": 7.2922281,
      "alt_m": -32768.0
    },
    {
      "lat": 62.7981978,
      "lon": 7.2923245,
      "alt_m": -32768.0
    },
    {
      "lat": 62.7981864,
      "lon": 7.2923788,
      "alt_m": -32768.0
    },
    {
      "lat": 62.798171,
      "lon": 7.2924293,
      "alt_m": -32768.0
    },
    {
      "lat": 62.7981589,
      "lon": 7.292458,
      "alt_m": -32768.0
    },
    {
      "lat": 62.7981453,
      "lon": 7.2924837,
      "alt_m": -32768.0
    },
    {
      "lat": 62.7981305,
      "lon": 7.2925049,
      "alt_m": -32768.0
    },
    {
      "lat": 62.7981145,
      "lon": 7.2925217,
      "alt_m": -32768.0
    },
    {
      "lat": 62.7980975,
      "lon": 7.2925341,
      "alt_m": -32768.0
    },
    {
      "lat": 62.7980804,
      "lon": 7.2925406,
      "alt_m": -32768.0
    },
    {
      "lat": 62.7980637,
      "lon": 7.292541,
      "alt_m": -32768.0
    },
    {
      "lat": 62.7980469,
      "lon": 7.2925358,
      "alt_m": -32768.0
    },
    {
      "lat": 62.7980313,
      "lon": 7.2925243,
      "alt_m": -32768.0
    },
    {
      "lat": 62.7980164,
      "lon": 7.2925042,
      "alt_m": -32768.0
    },
    {
      "lat": 62.7980027,
      "lon": 7.2924774,
      "alt_m": -32768.0
    },
    {
      "lat": 62.7979912,
      "lon": 7.292448,
      "alt_m": -32768.0
    },
    {
      "lat": 62.7979808,
      "lon": 7.2924024,
      "alt_m": -32768.0
    },
    {
      "lat": 62.7979715,
      "lon": 7.2923552,
      "alt_m": -32768.0
    },
    {
      "lat": 62.7979581,
      "lon": 7.2923087,
      "alt_m": -32768.0
    },
    {
      "lat": 62.7979421,
      "lon": 7.2922668,
      "alt_m": -32768.0
    },
    {
      "lat": 62.7979299,
      "lon": 7.2922442,
      "alt_m": -32768.0
    },
    {
      "lat": 62.7979164,
      "lon": 7.2922248,
      "alt_m": -32768.0
    },
    {
      "lat": 62.7979022,
      "lon": 7.2922091,
      "alt_m": -32768.0
    },
    {
      "lat": 62.7978875,
      "lon": 7.2921974,
      "alt_m": -32768.0
    },
    {
      "lat": 62.7978722,
      "lon": 7.2921894,
      "alt_m": -32768.0
    },
    {
      "lat": 62.7978565,
      "lon": 7.2921854,
      "alt_m": -32768.0
    },
    {
      "lat": 62.7978314,
      "lon": 7.2921883,
      "alt_m": -32768.0
    },
    {
      "lat": 62.7978063,
      "lon": 7.2921993,
      "alt_m": -32768.0
    },
    {
      "lat": 62.7977816,
      "lon": 7.2922167,
      "alt_m": -32768.0
    },
    {
      "lat": 62.7977576,
      "lon": 7.2922403,
      "alt_m": -32768.0
    },
    {
      "lat": 62.797734,
      "lon": 7.2922696,
      "alt_m": -32768.0
    },
    {
      "lat": 62.7977123,
      "lon": 7.2923053,
      "alt_m": -32768.0
    },
    {
      "lat": 62.7976933,
      "lon": 7.2923501,
      "alt_m": -32768.0
    },
    {
      "lat": 62.7976773,
      "lon": 7.2923989,
      "alt_m": -32768.0
    },
    {
      "lat": 62.7976663,
      "lon": 7.2924403,
      "alt_m": -32768.0
    },
    {
      "lat": 62.7976566,
      "lon": 7.2924873,
      "alt_m": -32768.0
    },
    {
      "lat": 62.7976253,
      "lon": 7.2926922,
      "alt_m": -32768.0
    },
    {
      "lat": 62.7976196,
      "lon": 7.2927436,
      "alt_m": -32768.0
    },
    {
      "lat": 62.7976163,
      "lon": 7.2928008,
      "alt_m": -32768.0
    },
    {
      "lat": 62.7976156,
      "lon": 7.2929986,
      "alt_m": -32768.0
    },
    {
      "lat": 62.7976244,
      "lon": 7.2932653,
      "alt_m": -32768.0
    },
    {
      "lat": 62.7977286,
      "lon": 7.2945502,
      "alt_m": -32768.0
    },
    {
      "lat": 62.797736,
      "lon": 7.294604,
      "alt_m": -32768.0
    },
    {
      "lat": 62.7977446,
      "lon": 7.2946428,
      "alt_m": -32768.0
    },
    {
      "lat": 62.7977607,
      "lon": 7.2946928,
      "alt_m": -32768.0
    },
    {
      "lat": 62.7977799,
      "lon": 7.2947377,
      "alt_m": -32768.0
    },
    {
      "lat": 62.7977981,
      "lon": 7.2947705,
      "alt_m": -32768.0
    },
    {
      "lat": 62.7978177,
      "lon": 7.2947967,
      "alt_m": -32768.0
    },
    {
      "lat": 62.7978386,
      "lon": 7.2948161,
      "alt_m": -32768.0
    },
    {
      "lat": 62.7978604,
      "lon": 7.2948293,
      "alt_m": -32768.0
    },
    {
      "lat": 62.7979059,
      "lon": 7.2948381,
      "alt_m": -32768.0
    },
    {
      "lat": 62.7980486,
      "lon": 7.2948392,
      "alt_m": -32768.0
    },
    {
      "lat": 62.798096,
      "lon": 7.2948518,
      "alt_m": -32768.0
    },
    {
      "lat": 62.7981398,
      "lon": 7.294876,
      "alt_m": -32768.0
    },
    {
      "lat": 62.7981916,
      "lon": 7.294915,
      "alt_m": -32768.0
    },
    {
      "lat": 62.7982172,
      "lon": 7.2949296,
      "alt_m": -32768.0
    },
    {
      "lat": 62.7982426,
      "lon": 7.294937,
      "alt_m": -32768.0
    },
    {
      "lat": 62.7982588,
      "lon": 7.2949358,
      "alt_m": -32768.0
    },
    {
      "lat": 62.7982748,
      "lon": 7.2949302,
      "alt_m": -32768.0
    },
    {
      "lat": 62.7982898,
      "lon": 7.2949187,
      "alt_m": -32768.0
    },
    {
      "lat": 62.798301,
      "lon": 7.2949044,
      "alt_m": -32768.0
    },
    {
      "lat": 62.7983119,
      "lon": 7.2948861,
      "alt_m": -32768.0
    },
    {
      "lat": 62.7983215,
      "lon": 7.2948648,
      "alt_m": -32768.0
    },
    {
      "lat": 62.798329,
      "lon": 7.2948418,
      "alt_m": -32768.0
    },
    {
      "lat": 62.7983343,
      "lon": 7.2948166,
      "alt_m": -32768.0
    },
    {
      "lat": 62.7983378,
      "lon": 7.2947888,
      "alt_m": -32768.0
    },
    {
      "lat": 62.7983395,
      "lon": 7.29476,
      "alt_m": -32768.0
    },
    {
      "lat": 62.7983393,
      "lon": 7.2947324,
      "alt_m": -32768.0
    },
    {
      "lat": 62.7983368,
      "lon": 7.2947054,
      "alt_m": -32768.0
    },
    {
      "lat": 62.7983323,
      "lon": 7.2946783,
      "alt_m": -32768.0
    },
    {
      "lat": 62.7983261,
      "lon": 7.2946526,
      "alt_m": -32768.0
    },
    {
      "lat": 62.798319,
      "lon": 7.29463,
      "alt_m": -32768.0
    },
    {
      "lat": 62.7983082,
      "lon": 7.2946062,
      "alt_m": -32768.0
    },
    {
      "lat": 62.7982955,
      "lon": 7.2945863,
      "alt_m": -32768.0
    },
    {
      "lat": 62.7982818,
      "lon": 7.2945693,
      "alt_m": -32768.0
    },
    {
      "lat": 62.7982585,
      "lon": 7.2945485,
      "alt_m": -32768.0
    },
    {
      "lat": 62.7982315,
      "lon": 7.2945321,
      "alt_m": -32768.0
    },
    {
      "lat": 62.7981302,
      "lon": 7.2944907,
      "alt_m": -32768.0
    },
    {
      "lat": 62.7980834,
      "lon": 7.2944608,
      "alt_m": -32768.0
    },
    {
      "lat": 62.7980614,
      "lon": 7.2944399,
      "alt_m": -32768.0
    },
    {
      "lat": 62.7980405,
      "lon": 7.2944147,
      "alt_m": -32768.0
    },
    {
      "lat": 62.7980206,
      "lon": 7.2943847,
      "alt_m": -32768.0
    },
    {
      "lat": 62.7980026,
      "lon": 7.2943501,
      "alt_m": -32768.0
    },
    {
      "lat": 62.7979873,
      "lon": 7.294311,
      "alt_m": -32768.0
    },
    {
      "lat": 62.7979745,
      "lon": 7.2942679,
      "alt_m": -32768.0
    },
    {
      "lat": 62.7979644,
      "lon": 7.2942214,
      "alt_m": -32768.0
    },
    {
      "lat": 62.7979571,
      "lon": 7.2941723,
      "alt_m": -32768.0
    },
    {
      "lat": 62.7979532,
      "lon": 7.2941209,
      "alt_m": -32768.0
    },
    {
      "lat": 62.7979522,
      "lon": 7.2940685,
      "alt_m": -32768.0
    },
    {
      "lat": 62.7979539,
      "lon": 7.2940167,
      "alt_m": -32768.0
    },
    {
      "lat": 62.7979581,
      "lon": 7.2939651,
      "alt_m": -32768.0
    },
    {
      "lat": 62.7979735,
      "lon": 7.2938612,
      "alt_m": -32768.0
    },
    {
      "lat": 62.7979798,
      "lon": 7.2938094,
      "alt_m": -32768.0
    },
    {
      "lat": 62.7979837,
      "lon": 7.2937573,
      "alt_m": -32768.0
    },
    {
      "lat": 62.7979835,
      "lon": 7.2937052,
      "alt_m": -32768.0
    },
    {
      "lat": 62.7979804,
      "lon": 7.2936533,
      "alt_m": -32768.0
    },
    {
      "lat": 62.7979752,
      "lon": 7.2936012,
      "alt_m": -32768.0
    },
    {
      "lat": 62.7979676,
      "lon": 7.2935506,
      "alt_m": -32768.0
    },
    {
      "lat": 62.7979582,
      "lon": 7.2935049,
      "alt_m": -32768.0
    },
    {
      "lat": 62.7979451,
      "lon": 7.2934586,
      "alt_m": -32768.0
    },
    {
      "lat": 62.7979106,
      "lon": 7.2933781,
      "alt_m": -32768.0
    },
    {
      "lat": 62.7978759,
      "lon": 7.2932984,
      "alt_m": -32768.0
    },
    {
      "lat": 62.7978623,
      "lon": 7.2932549,
      "alt_m": -32768.0
    },
    {
      "lat": 62.7978526,
      "lon": 7.2932114,
      "alt_m": -32768.0
    },
    {
      "lat": 62.7978469,
      "lon": 7.2931752,
      "alt_m": -32768.0
    },
    {
      "lat": 62.7978429,
      "lon": 7.2931369,
      "alt_m": -32768.0
    },
    {
      "lat": 62.7978416,
      "lon": 7.2930993,
      "alt_m": -32768.0
    },
    {
      "lat": 62.7978427,
      "lon": 7.2930732,
      "alt_m": -32768.0
    },
    {
      "lat": 62.7978452,
      "lon": 7.2930472,
      "alt_m": -32768.0
    },
    {
      "lat": 62.7978492,
      "lon": 7.2930223,
      "alt_m": -32768.0
    },
    {
      "lat": 62.7978546,
      "lon": 7.2929995,
      "alt_m": -32768.0
    },
    {
      "lat": 62.7978648,
      "lon": 7.2929714,
      "alt_m": -32768.0
    },
    {
      "lat": 62.7978776,
      "lon": 7.2929465,
      "alt_m": -32768.0
    },
    {
      "lat": 62.7978917,
      "lon": 7.2929259,
      "alt_m": -32768.0
    },
    {
      "lat": 62.7979073,
      "lon": 7.2929095,
      "alt_m": -32768.0
    },
    {
      "lat": 62.7979242,
      "lon": 7.2928977,
      "alt_m": -32768.0
    },
    {
      "lat": 62.7979416,
      "lon": 7.2928904,
      "alt_m": -32768.0
    },
    {
      "lat": 62.7979675,
      "lon": 7.2928883,
      "alt_m": -32768.0
    },
    {
      "lat": 62.7979967,
      "lon": 7.292897,
      "alt_m": -32768.0
    },
    {
      "lat": 62.7980668,
      "lon": 7.2929426,
      "alt_m": -32768.0
    },
    {
      "lat": 62.7981354,
      "lon": 7.292999,
      "alt_m": -32768.0
    },
    {
      "lat": 62.7981844,
      "lon": 7.2930477,
      "alt_m": -32768.0
    },
    {
      "lat": 62.7982326,
      "lon": 7.2931102,
      "alt_m": -32768.0
    },
    {
      "lat": 62.7982772,
      "lon": 7.2931842,
      "alt_m": -32768.0
    },
    {
      "lat": 62.7983212,
      "lon": 7.2932703,
      "alt_m": -32768.0
    },
    {
      "lat": 62.7983621,
      "lon": 7.2933627,
      "alt_m": -32768.0
    },
    {
      "lat": 62.7983903,
      "lon": 7.2934407,
      "alt_m": -32768.0
    },
    {
      "lat": 62.7984149,
      "lon": 7.2935253,
      "alt_m": -32768.0
    },
    {
      "lat": 62.7984423,
      "lon": 7.2936405,
      "alt_m": -32768.0
    },
    {
      "lat": 62.798631,
      "lon": 7.2946596,
      "alt_m": -32768.0
    },
    {
      "lat": 62.7986474,
      "lon": 7.2947772,
      "alt_m": -32768.0
    },
    {
      "lat": 62.7986569,
      "lon": 7.294894,
      "alt_m": -32768.0
    },
    {
      "lat": 62.7986577,
      "lon": 7.2949518,
      "alt_m": -32768.0
    },
    {
      "lat": 62.7986559,
      "lon": 7.2950094,
      "alt_m": -32768.0
    },
    {
      "lat": 62.7986514,
      "lon": 7.2950676,
      "alt_m": -32768.0
    },
    {
      "lat": 62.7986441,
      "lon": 7.2951241,
      "alt_m": -32768.0
    },
    {
      "lat": 62.7986338,
      "lon": 7.2951764,
      "alt_m": -32768.0
    },
    {
      "lat": 62.7986207,
      "lon": 7.2952255,
      "alt_m": -32768.0
    },
    {
      "lat": 62.7986051,
      "lon": 7.2952716,
      "alt_m": -32768.0
    },
    {
      "lat": 62.7985872,
      "lon": 7.2953134,
      "alt_m": -32768.0
    },
    {
      "lat": 62.7985671,
      "lon": 7.2953498,
      "alt_m": -32768.0
    },
    {
      "lat": 62.7985451,
      "lon": 7.2953802,
      "alt_m": -32768.0
    },
    {
      "lat": 62.7985209,
      "lon": 7.2954037,
      "alt_m": -32768.0
    },
    {
      "lat": 62.7984955,
      "lon": 7.2954198,
      "alt_m": -32768.0
    },
    {
      "lat": 62.7984695,
      "lon": 7.2954277,
      "alt_m": -32768.0
    },
    {
      "lat": 62.7984433,
      "lon": 7.2954282,
      "alt_m": -32768.0
    },
    {
      "lat": 62.7984184,
      "lon": 7.2954222,
      "alt_m": -32768.0
    },
    {
      "lat": 62.7983916,
      "lon": 7.295409,
      "alt_m": -32768.0
    },
    {
      "lat": 62.7982876,
      "lon": 7.2953283,
      "alt_m": -32768.0
    },
    {
      "lat": 62.7982318,
      "lon": 7.295302,
      "alt_m": -32768.0
    },
    {
      "lat": 62.7981752,
      "lon": 7.2952965,
      "alt_m": -32768.0
    },
    {
      "lat": 62.798117,
      "lon": 7.2953056,
      "alt_m": -32768.0
    },
    {
      "lat": 62.7980604,
      "lon": 7.2953332,
      "alt_m": -32768.0
    },
    {
      "lat": 62.7980341,
      "lon": 7.2953552,
      "alt_m": -32768.0
    },
    {
      "lat": 62.7980089,
      "lon": 7.2953821,
      "alt_m": -32768.0
    },
    {
      "lat": 62.7979625,
      "lon": 7.295449,
      "alt_m": -32768.0
    },
    {
      "lat": 62.7978788,
      "lon": 7.2955971,
      "alt_m": -32768.0
    },
    {
      "lat": 62.7978553,
      "lon": 7.2956253,
      "alt_m": -32768.0
    },
    {
      "lat": 62.7978324,
      "lon": 7.2956436,
      "alt_m": -32768.0
    },
    {
      "lat": 62.7978069,
      "lon": 7.295654,
      "alt_m": -32768.0
    },
    {
      "lat": 62.797781,
      "lon": 7.2956557,
      "alt_m": -32768.0
    },
    {
      "lat": 62.7977568,
      "lon": 7.2956492,
      "alt_m": -32768.0
    },
    {
      "lat": 62.7977335,
      "lon": 7.2956348,
      "alt_m": -32768.0
    },
    {
      "lat": 62.7977113,
      "lon": 7.2956124,
      "alt_m": -32768.0
    },
    {
      "lat": 62.7976908,
      "lon": 7.2955834,
      "alt_m": -32768.0
    },
    {
      "lat": 62.7976726,
      "lon": 7.2955498,
      "alt_m": -32768.0
    },
    {
      "lat": 62.7976566,
      "lon": 7.2955113,
      "alt_m": -32768.0
    },
    {
      "lat": 62.7976432,
      "lon": 7.2954674,
      "alt_m": -32768.0
    },
    {
      "lat": 62.797632,
      "lon": 7.2954201,
      "alt_m": -32768.0
    },
    {
      "lat": 62.7976149,
      "lon": 7.2953181,
      "alt_m": -32768.0
    },
    {
      "lat": 62.7975694,
      "lon": 7.2948607,
      "alt_m": -32768.0
    },
    {
      "lat": 62.797492,
      "lon": 7.2939689,
      "alt_m": 0.0
    }
  ]
}