{
  "source_file": "05b5a73y.tkk",
  "full_name": "New Hampshire Motor Speedway NHMS Road",
  "name": "New Hampshire Motor Speedway",
  "venue_id": "05b5a73y",
  "short_name": "NHMS Road",
  "country": "US",
  "track_length_m": 2472.4,
  "reference_point": {
    "lat": 43.362408,
    "lon": -71.460268,
    "alt_m": 149.0
  },
  "start_finish": {
    "lat": 43.3631522,
    "lon": -71.462069
  },
  "surface": "asphalt",
  "timezone": "America/New_York",
  "timezone_label": "(UTC-05:00) Eastern Time (US & Canada)",
  "contact": {
    "city": "Loudon",
    "address": "1122 Route 106 North",
    "postal_code": "03307",
    "phone": "+1 603 783 4931",
    "url": "https://www.nhms.com/"
  },
  "start_finish_line": {
    "p1": {
      "lat": 43.3630979,
      "lon": -71.4618559
    },
    "p2": {
      "lat": 43.3632065,
      "lon": -71.4622821
    }
  },
  "logo_file": "New Hampshire Motor Speedway NHMS Road_logo.png",
  "svg_file": "New Hampshire Motor Speedway NHMS Road.svg",
  "gps_points": [
    {
      "lat": 43.3631522,
      "lon": -71.462069,
      "alt_m": 153.0
    },
    {
      "lat": 43.3622509,
      "lon": -71.4625038,
      "alt_m": 157.0
    },
    {
      "lat": 43.3613392,
      "lon": -71.4628752,
      "alt_m": 157.0
    },
    {
      "lat": 43.361175,
      "lon": -71.4629211,
      "alt_m": 157.0
    },
    {
      "lat": 43.3610381,
      "lon": -71.4629421,
      "alt_m": 157.0
    },
    {
      "lat": 43.360939,
      "lon": -71.4629406,
      "alt_m": 157.0
    },
    {
      "lat": 43.3608511,
      "lon": -71.4629259,
      "alt_m": 157.0
    },
    {
      "lat": 43.3607888,
      "lon": -71.462906,
      "alt_m": 157.0
    },
    {
      "lat": 43.3607324,
      "lon": -71.4628782,
      "alt_m": 157.0
    },
    {
      "lat": 43.3606779,
      "lon": -71.4628419,
      "alt_m": 157.0
    },
    {
      "lat": 43.3606264,
      "lon": -71.462797,
      "alt_m": 157.0
    },
    {
      "lat": 43.3605674,
      "lon": -71.4627317,
      "alt_m": 157.0
    },
    {
      "lat": 43.3605145,
      "lon": -71.4626596,
      "alt_m": 157.0
    },
    {
      "lat": 43.3604765,
      "lon": -71.4625956,
      "alt_m": 157.0
    },
    {
      "lat": 43.3604448,
      "lon": -71.4625271,
      "alt_m": 157.0
    },
    {
      "lat": 43.3604124,
      "lon": -71.4624367,
      "alt_m": 149.0
    },
    {
      "lat": 43.3603877,
      "lon": -71.4623376,
      "alt_m": 149.0
    },
    {
      "lat": 43.3603732,
      "lon": -71.4622181,
      "alt_m": 149.0
    },
    {
      "lat": 43.3603672,
      "lon": -71.4620913,
      "alt_m": 149.0
    },
    {
      "lat": 43.3603707,
      "lon": -71.4617985,
      "alt_m": 149.0
    },
    {
      "lat": 43.360362,
      "lon": -71.4617141,
      "alt_m": 149.0
    },
    {
      "lat": 43.3603479,
      "lon": -71.4616393,
      "alt_m": 149.0
    },
    {
      "lat": 43.3603316,
      "lon": -71.461579,
      "alt_m": 149.0
    },
    {
      "lat": 43.3603108,
      "lon": -71.4615224,
      "alt_m": 149.0
    },
    {
      "lat": 43.3602871,
      "lon": -71.4614712,
      "alt_m": 149.0
    },
    {
      "lat": 43.360255,
      "lon": -71.4614158,
      "alt_m": 149.0
    },
    {
      "lat": 43.3601538,
      "lon": -71.4612798,
      "alt_m": 149.0
    },
    {
      "lat": 43.3600511,
      "lon": -71.4611365,
      "alt_m": 149.0
    },
    {
      "lat": 43.3600111,
      "lon": -71.4610566,
      "alt_m": 149.0
    },
    {
      "lat": 43.359983,
      "lon": -71.4609787,
      "alt_m": 149.0
    },
    {
      "lat": 43.3599611,
      "lon": -71.4608895,
      "alt_m": 149.0
    },
    {
      "lat": 43.3599478,
      "lon": -71.4607997,
      "alt_m": 149.0
    },
    {
      "lat": 43.3599426,
      "lon": -71.4607231,
      "alt_m": 149.0
    },
    {
      "lat": 43.3599446,
      "lon": -71.4606458,
      "alt_m": 149.0
    },
    {
      "lat": 43.3599557,
      "lon": -71.4605517,
      "alt_m": 149.0
    },
    {
      "lat": 43.3599774,
      "lon": -71.4604546,
      "alt_m": 149.0
    },
    {
      "lat": 43.3600168,
      "lon": -71.4603451,
      "alt_m": 149.0
    },
    {
      "lat": 43.3600666,
      "lon": -71.4602396,
      "alt_m": 149.0
    },
    {
      "lat": 43.3601133,
      "lon": -71.4601574,
      "alt_m": 149.0
    },
    {
      "lat": 43.3601722,
      "lon": -71.4600759,
      "alt_m": 149.0
    },
    {
      "lat": 43.3604504,
      "lon": -71.4597977,
      "alt_m": 149.0
    },
    {
      "lat": 43.3606773,
      "lon": -71.4596285,
      "alt_m": 149.0
    },
    {
      "lat": 43.3612442,
      "lon": -71.4593884,
      "alt_m": 149.0
    },
    {
      "lat": 43.3617855,
      "lon": -71.4592689,
      "alt_m": 149.0
    },
    {
      "lat": 43.3626392,
      "lon": -71.4591757,
      "alt_m": 146.0
    },
    {
      "lat": 43.3626952,
      "lon": -71.4591642,
      "alt_m": 146.0
    },
    {
      "lat": 43.3627344,
      "lon": -71.459151,
      "alt_m": 146.0
    },
    {
      "lat": 43.3627604,
      "lon": -71.4591379,
      "alt_m": 146.0
    },
    {
      "lat": 43.3627826,
      "lon": -71.4591206,
      "alt_m": 146.0
    },
    {
      "lat": 43.3627996,
      "lon": -71.4591009,
      "alt_m": 146.0
    },
    {
      "lat": 43.3628151,
      "lon": -71.4590773,
      "alt_m": 146.0
    },
    {
      "lat": 43.3628288,
      "lon": -71.4590521,
      "alt_m": 146.0
    },
    {
      "lat": 43.3628464,
      "lon": -71.4590096,
      "alt_m": 146.0
    },
    {
      "lat": 43.3628596,
      "lon": -71.4589625,
      "alt_m": 146.0
    },
    {
      "lat": 43.3628711,
      "lon": -71.4588981,
      "alt_m": 146.0
    },
    {
      "lat": 43.3628764,
      "lon": -71.4588293,
      "alt_m": 146.0
    },
    {
      "lat": 43.3628739,
      "lon": -71.4587551,
      "alt_m": 146.0
    },
    {
      "lat": 43.3628647,
      "lon": -71.4586823,
      "alt_m": 146.0
    },
    {
      "lat": 43.3628524,
      "lon": -71.4586224,
      "alt_m": 146.0
    },
    {
      "lat": 43.3628339,
      "lon": -71.4585643,
      "alt_m": 146.0
    },
    {
      "lat": 43.362803,
      "lon": -71.4584964,
      "alt_m": 146.0
    },
    {
      "lat": 43.3627654,
      "lon": -71.4584325,
      "alt_m": 146.0
    },
    {
      "lat": 43.36273,
      "lon": -71.458386,
      "alt_m": 146.0
    },
    {
      "lat": 43.3626895,
      "lon": -71.458344,
      "alt_m": 146.0
    },
    {
      "lat": 43.3626341,
      "lon": -71.4582975,
      "alt_m": 151.0
    },
    {
      "lat": 43.3625742,
      "lon": -71.4582574,
      "alt_m": 151.0
    },
    {
      "lat": 43.3625218,
      "lon": -71.4582317,
      "alt_m": 151.0
    },
    {
      "lat": 43.3624681,
      "lon": -71.4582134,
      "alt_m": 159.0
    },
    {
      "lat": 43.3624131,
      "lon": -71.458202,
      "alt_m": 159.0
    },
    {
      "lat": 43.3623535,
      "lon": -71.4581975,
      "alt_m": 159.0
    },
    {
      "lat": 43.3621671,
      "lon": -71.4582156,
      "alt_m": 159.0
    },
    {
      "lat": 43.362007,
      "lon": -71.4582651,
      "alt_m": 159.0
    },
    {
      "lat": 43.3617789,
      "lon": -71.4583777,
      "alt_m": 149.0
    },
    {
      "lat": 43.3614575,
      "lon": -71.4585755,
      "alt_m": 149.0
    },
    {
      "lat": 43.3611479,
      "lon": -71.4588064,
      "alt_m": 149.0
    },
    {
      "lat": 43.3607475,
      "lon": -71.459149,
      "alt_m": 149.0
    },
    {
      "lat": 43.3602257,
      "lon": -71.4595784,
      "alt_m": 149.0
    },
    {
      "lat": 43.3599877,
      "lon": -71.459718,
      "alt_m": 149.0
    },
    {
      "lat": 43.3599297,
      "lon": -71.4597397,
      "alt_m": 149.0
    },
    {
      "lat": 43.359876,
      "lon": -71.4597507,
      "alt_m": 149.0
    },
    {
      "lat": 43.3598218,
      "lon": -71.4597524,
      "alt_m": 149.0
    },
    {
      "lat": 43.3597685,
      "lon": -71.459745,
      "alt_m": 149.0
    },
    {
      "lat": 43.3597162,
      "lon": -71.4597283,
      "alt_m": 149.0
    },
    {
      "lat": 43.3596666,
      "lon": -71.4597029,
      "alt_m": 149.0
    },
    {
      "lat": 43.3596193,
      "lon": -71.4596678,
      "alt_m": 149.0
    },
    {
      "lat": 43.3595769,
      "lon": -71.4596252,
      "alt_m": 149.0
    },
    {
      "lat": 43.3595387,
      "lon": -71.4595741,
      "alt_m": 149.0
    },
    {
      "lat": 43.3595071,
      "lon": -71.4595172,
      "alt_m": 149.0
    },
    {
      "lat": 43.3594823,
      "lon": -71.4594531,
      "alt_m": 149.0
    },
    {
      "lat": 43.359465,
      "lon": -71.4593853,
      "alt_m": 149.0
    },
    {
      "lat": 43.3594549,
      "lon": -71.4593138,
      "alt_m": 149.0
    },
    {
      "lat": 43.3594523,
      "lon": -71.4592407,
      "alt_m": 149.0
    },
    {
      "lat": 43.3594565,
      "lon": -71.4591671,
      "alt_m": 149.0
    },
    {
      "lat": 43.3594695,
      "lon": -71.4590901,
      "alt_m": 149.0
    },
    {
      "lat": 43.3595011,
      "lon": -71.4589811,
      "alt_m": 149.0
    },
    {
      "lat": 43.3595474,
      "lon": -71.4588685,
      "alt_m": 149.0
    },
    {
      "lat": 43.3596136,
      "lon": -71.4587512,
      "alt_m": 149.0
    },
    {
      "lat": 43.3596919,
      "lon": -71.4586423,
      "alt_m": 149.0
    },
    {
      "lat": 43.3597698,
      "lon": -71.458558,
      "alt_m": 149.0
    },
    {
      "lat": 43.3598545,
      "lon": -71.458484,
      "alt_m": 149.0
    },
    {
      "lat": 43.3599492,
      "lon": -71.4584146,
      "alt_m": 149.0
    },
    {
      "lat": 43.3600418,
      "lon": -71.4583604,
      "alt_m": 149.0
    },
    {
      "lat": 43.3600937,
      "lon": -71.4583388,
      "alt_m": 149.0
    },
    {
      "lat": 43.3601496,
      "lon": -71.4583257,
      "alt_m": 152.0
    },
    {
      "lat": 43.3604221,
      "lon": -71.4583205,
      "alt_m": 159.0
    },
    {
      "lat": 43.3607811,
      "lon": -71.4583638,
      "alt_m": 149.0
    },
    {
      "lat": 43.3609874,
      "lon": -71.4583501,
      "alt_m": 149.0
    },
    {
      "lat": 43.3611861,
      "lon": -71.4583042,
      "alt_m": 159.0
    },
    {
      "lat": 43.3614165,
      "lon": -71.4582124,
      "alt_m": 159.0
    },
    {
      "lat": 43.3616042,
      "lon": -71.4581037,
      "alt_m": 159.0
    },
    {
      "lat": 43.3618184,
      "lon": -71.4579409,
      "alt_m": 159.0
    },
    {
      "lat": 43.3621742,
      "lon": -71.4576528,
      "alt_m": 159.0
    },
    {
      "lat": 43.3622618,
      "lon": -71.4576156,
      "alt_m": 159.0
    },
    {
      "lat": 43.3623405,
      "lon": -71.457598,
      "alt_m": 159.0
    },
    {
      "lat": 43.3623971,
      "lon": -71.4575939,
      "alt_m": 159.0
    },
    {
      "lat": 43.3624513,
      "lon": -71.4575988,
      "alt_m": 159.0
    },
    {
      "lat": 43.3625088,
      "lon": -71.4576121,
      "alt_m": 151.0
    },
    {
      "lat": 43.3625661,
      "lon": -71.4576348,
      "alt_m": 151.0
    },
    {
      "lat": 43.3626326,
      "lon": -71.4576731,
      "alt_m": 151.0
    },
    {
      "lat": 43.3626971,
      "lon": -71.4577245,
      "alt_m": 151.0
    },
    {
      "lat": 43.3627679,
      "lon": -71.4578034,
      "alt_m": 151.0
    },
    {
      "lat": 43.3628328,
      "lon": -71.4578982,
      "alt_m": 151.0
    },
    {
      "lat": 43.3629568,
      "lon": -71.4581674,
      "alt_m": 151.0
    },
    {
      "lat": 43.363056,
      "lon": -71.4584279,
      "alt_m": 146.0
    },
    {
      "lat": 43.3630912,
      "lon": -71.4584899,
      "alt_m": 146.0
    },
    {
      "lat": 43.3631283,
      "lon": -71.4585435,
      "alt_m": 146.0
    },
    {
      "lat": 43.3631676,
      "lon": -71.4585964,
      "alt_m": 146.0
    },
    {
      "lat": 43.3632107,
      "lon": -71.4586443,
      "alt_m": 146.0
    },
    {
      "lat": 43.3632569,
      "lon": -71.458683,
      "alt_m": 146.0
    },
    {
      "lat": 43.363307,
      "lon": -71.4587151,
      "alt_m": 146.0
    },
    {
      "lat": 43.363359,
      "lon": -71.4587391,
      "alt_m": 146.0
    },
    {
      "lat": 43.3634154,
      "lon": -71.4587573,
      "alt_m": 146.0
    },
    {
      "lat": 43.3635677,
      "lon": -71.4587829,
      "alt_m": 146.0
    },
    {
      "lat": 43.3637603,
      "lon": -71.4587705,
      "alt_m": 146.0
    },
    {
      "lat": 43.3639648,
      "lon": -71.4587191,
      "alt_m": 146.0
    },
    {
      "lat": 43.3642951,
      "lon": -71.4586361,
      "alt_m": 146.0
    },
    {
      "lat": 43.3644102,
      "lon": -71.4586295,
      "alt_m": 146.0
    },
    {
      "lat": 43.3645197,
      "lon": -71.4586378,
      "alt_m": 146.0
    },
    {
      "lat": 43.3646288,
      "lon": -71.4586599,
      "alt_m": 154.0
    },
    {
      "lat": 43.3647396,
      "lon": -71.4586969,
      "alt_m": 154.0
    },
    {
      "lat": 43.3648906,
      "lon": -71.458766,
      "alt_m": 154.0
    },
    {
      "lat": 43.3650308,
      "lon": -71.4588488,
      "alt_m": 154.0
    },
    {
      "lat": 43.3651103,
      "lon": -71.4589123,
      "alt_m": 154.0
    },
    {
      "lat": 43.3651766,
      "lon": -71.458981,
      "alt_m": 154.0
    },
    {
      "lat": 43.3652363,
      "lon": -71.4590591,
      "alt_m": 154.0
    },
    {
      "lat": 43.3652845,
      "lon": -71.4591396,
      "alt_m": 154.0
    },
    {
      "lat": 43.3653118,
      "lon": -71.4592014,
      "alt_m": 154.0
    },
    {
      "lat": 43.3653316,
      "lon": -71.4592655,
      "alt_m": 154.0
    },
    {
      "lat": 43.3653501,
      "lon": -71.4593515,
      "alt_m": 154.0
    },
    {
      "lat": 43.3653611,
      "lon": -71.4594429,
      "alt_m": 154.0
    },
    {
      "lat": 43.3653636,
      "lon": -71.4595365,
      "alt_m": 154.0
    },
    {
      "lat": 43.3653559,
      "lon": -71.4596384,
      "alt_m": 154.0
    },
    {
      "lat": 43.3653253,
      "lon": -71.4598064,
      "alt_m": 154.0
    },
    {
      "lat": 43.3652757,
      "lon": -71.4599988,
      "alt_m": 154.0
    },
    {
      "lat": 43.3650652,
      "lon": -71.4606165,
      "alt_m": 153.0
    },
    {
      "lat": 43.3649288,
      "lon": -71.4608859,
      "alt_m": 153.0
    },
    {
      "lat": 43.3648466,
      "lon": -71.4610098,
      "alt_m": 153.0
    },
    {
      "lat": 43.3647525,
      "lon": -71.4611282,
      "alt_m": 153.0
    },
    {
      "lat": 43.3646367,
      "lon": -71.4612505,
      "alt_m": 153.0
    },
    {
      "lat": 43.3645015,
      "lon": -71.4613682,
      "alt_m": 153.0
    },
    {
      "lat": 43.3640812,
      "lon": -71.4616357,
      "alt_m": 153.0
    },
    {
      "lat": 43.3635914,
      "lon": -71.4618681,
      "alt_m": 153.0
    },
    {
      "lat": 43.3631671,
      "lon": -71.4620618,
      "alt_m": 153.0
    },
    {
      "lat": 43.3631522,
      "lon": -71.462069,
      "alt_m": 153.0
    }
  ]
}