{
  "source_file": "1gl04zxm.tkk",
  "full_name": "SpeedFun Karting SpeedFun CW",
  "name": "SpeedFun Karting",
  "venue_id": "1gl04zxm",
  "short_name": "SpeedFun CW",
  "country": "FR",
  "track_length_m": 700.6,
  "reference_point": {
    "lat": 46.2924027,
    "lon": -0.5071472,
    "alt_m": 21.0
  },
  "start_finish": {
    "lat": 46.2920685,
    "lon": -0.50747
  },
  "surface": "asphalt",
  "timezone": "Europe/Paris",
  "timezone_label": "(UTC+01:00) Brussels, Copenhagen, Madrid, Paris",
  "contact": {
    "city": "Bessines",
    "address": "140 Route de la Rochelle",
    "postal_code": "79000",
    "phone": "+33 5 49 76 29 46",
    "url": "http://speed-fun-karting.com/"
  },
  "start_finish_line": {
    "p1": {
      "lat": 46.2920987,
      "lon": -0.5075189
    },
    "p2": {
      "lat": 46.2920383,
      "lon": -0.5074211
    }
  },
  "logo_file": "SpeedFun Karting SpeedFun CW_logo.png",
  "svg_file": "SpeedFun Karting SpeedFun CW.svg",
  "gps_points": [
    {
      "lat": 46.2920685,
      "lon": -0.50747,
      "alt_m": 0.0
    },
    {
      "lat": 46.2920923,
      "lon": -0.5074414,
      "alt_m": 21.0
    },
    {
      "lat": 46.2921801,
      "lon": -0.5073491,
      "alt_m": 21.0
    },
    {
      "lat": 46.2922202,
      "lon": -0.5073144,
      "alt_m": 21.0
    },
    {
      "lat": 46.2922529,
      "lon": -0.5072901,
      "alt_m": 21.0
    },
    {
      "lat": 46.2922908,
      "lon": -0.5072736,
      "alt_m": 21.0
    },
    {
      "lat": 46.2923227,
      "lon": -0.5072691,
      "alt_m": 21.0
    },
    {
      "lat": 46.2923513,
      "lon": -0.5072695,
      "alt_m": 21.0
    },
    {
      "lat": 46.2923743,
      "lon": -0.5072815,
      "alt_m": 21.0
    },
    {
      "lat": 46.2923934,
      "lon": -0.5072999,
      "alt_m": 21.0
    },
    {
      "lat": 46.2924134,
      "lon": -0.5073234,
      "alt_m": 21.0
    },
    {
      "lat": 46.2924266,
      "lon": -0.5073452,
      "alt_m": 21.0
    },
    {
      "lat": 46.2924341,
      "lon": -0.5073721,
      "alt_m": 21.0
    },
    {
      "lat": 46.2924382,
      "lon": -0.507402,
      "alt_m": 21.0
    },
    {
      "lat": 46.2924355,
      "lon": -0.5074361,
      "alt_m": 21.0
    },
    {
      "lat": 46.2924271,
      "lon": -0.5074725,
      "alt_m": 21.0
    },
    {
      "lat": 46.2924155,
      "lon": -0.507503,
      "alt_m": 21.0
    },
    {
      "lat": 46.2923993,
      "lon": -0.5075337,
      "alt_m": 21.0
    },
    {
      "lat": 46.2923801,
      "lon": -0.5075556,
      "alt_m": 21.0
    },
    {
      "lat": 46.2923579,
      "lon": -0.5075705,
      "alt_m": 21.0
    },
    {
      "lat": 46.2923364,
      "lon": -0.5075809,
      "alt_m": 21.0
    },
    {
      "lat": 46.2922137,
      "lon": -0.5076025,
      "alt_m": 21.0
    },
    {
      "lat": 46.2921784,
      "lon": -0.5076146,
      "alt_m": 21.0
    },
    {
      "lat": 46.292155,
      "lon": -0.5076297,
      "alt_m": 21.0
    },
    {
      "lat": 46.2921311,
      "lon": -0.5076547,
      "alt_m": 21.0
    },
    {
      "lat": 46.2921149,
      "lon": -0.5076807,
      "alt_m": 21.0
    },
    {
      "lat": 46.292102,
      "lon": -0.5077114,
      "alt_m": 21.0
    },
    {
      "lat": 46.2920984,
      "lon": -0.5077453,
      "alt_m": 21.0
    },
    {
      "lat": 46.2921039,
      "lon": -0.5077837,
      "alt_m": 21.0
    },
    {
      "lat": 46.292115,
      "lon": -0.5078152,
      "alt_m": 21.0
    },
    {
      "lat": 46.2921315,
      "lon": -0.5078371,
      "alt_m": 21.0
    },
    {
      "lat": 46.2921495,
      "lon": -0.5078501,
      "alt_m": 21.0
    },
    {
      "lat": 46.2921675,
      "lon": -0.5078534,
      "alt_m": 21.0
    },
    {
      "lat": 46.2921893,
      "lon": -0.5078518,
      "alt_m": 21.0
    },
    {
      "lat": 46.2926762,
      "lon": -0.5076756,
      "alt_m": 21.0
    },
    {
      "lat": 46.2927076,
      "lon": -0.5076603,
      "alt_m": 21.0
    },
    {
      "lat": 46.2927297,
      "lon": -0.5076435,
      "alt_m": 21.0
    },
    {
      "lat": 46.2927448,
      "lon": -0.5076224,
      "alt_m": 21.0
    },
    {
      "lat": 46.292754,
      "lon": -0.5076017,
      "alt_m": 21.0
    },
    {
      "lat": 46.2927607,
      "lon": -0.5075764,
      "alt_m": 21.0
    },
    {
      "lat": 46.2927608,
      "lon": -0.5075482,
      "alt_m": 21.0
    },
    {
      "lat": 46.2927547,
      "lon": -0.5075179,
      "alt_m": 21.0
    },
    {
      "lat": 46.2927451,
      "lon": -0.5074917,
      "alt_m": 22.0
    },
    {
      "lat": 46.2927287,
      "lon": -0.507462,
      "alt_m": 22.0
    },
    {
      "lat": 46.2927098,
      "lon": -0.5074374,
      "alt_m": 22.0
    },
    {
      "lat": 46.2926884,
      "lon": -0.5074179,
      "alt_m": 22.0
    },
    {
      "lat": 46.2926598,
      "lon": -0.5073971,
      "alt_m": 22.0
    },
    {
      "lat": 46.2926341,
      "lon": -0.5073791,
      "alt_m": 22.0
    },
    {
      "lat": 46.2926142,
      "lon": -0.5073631,
      "alt_m": 22.0
    },
    {
      "lat": 46.2925971,
      "lon": -0.5073426,
      "alt_m": 22.0
    },
    {
      "lat": 46.2925851,
      "lon": -0.5073138,
      "alt_m": 22.0
    },
    {
      "lat": 46.2925771,
      "lon": -0.5072786,
      "alt_m": 22.0
    },
    {
      "lat": 46.2925726,
      "lon": -0.5072394,
      "alt_m": 22.0
    },
    {
      "lat": 46.292575,
      "lon": -0.5071835,
      "alt_m": 22.0
    },
    {
      "lat": 46.2925859,
      "lon": -0.5071211,
      "alt_m": 22.0
    },
    {
      "lat": 46.2925952,
      "lon": -0.507088,
      "alt_m": 22.0
    },
    {
      "lat": 46.2926265,
      "lon": -0.5070258,
      "alt_m": 22.0
    },
    {
      "lat": 46.2926665,
      "lon": -0.5069672,
      "alt_m": 22.0
    },
    {
      "lat": 46.292709,
      "lon": -0.5069161,
      "alt_m": 22.0
    },
    {
      "lat": 46.2927425,
      "lon": -0.5068815,
      "alt_m": 22.0
    },
    {
      "lat": 46.2927795,
      "lon": -0.5068486,
      "alt_m": 22.0
    },
    {
      "lat": 46.2928012,
      "lon": -0.5068313,
      "alt_m": 22.0
    },
    {
      "lat": 46.2928252,
      "lon": -0.5068194,
      "alt_m": 22.0
    },
    {
      "lat": 46.2928483,
      "lon": -0.5068162,
      "alt_m": 22.0
    },
    {
      "lat": 46.2928674,
      "lon": -0.5068192,
      "alt_m": 22.0
    },
    {
      "lat": 46.2928879,
      "lon": -0.5068288,
      "alt_m": 22.0
    },
    {
      "lat": 46.2929078,
      "lon": -0.5068446,
      "alt_m": 22.0
    },
    {
      "lat": 46.2929267,
      "lon": -0.506869,
      "alt_m": 22.0
    },
    {
      "lat": 46.2929408,
      "lon": -0.5068978,
      "alt_m": 22.0
    },
    {
      "lat": 46.2929502,
      "lon": -0.5069297,
      "alt_m": 22.0
    },
    {
      "lat": 46.2929571,
      "lon": -0.5069695,
      "alt_m": 22.0
    },
    {
      "lat": 46.292958,
      "lon": -0.5070079,
      "alt_m": 22.0
    },
    {
      "lat": 46.2929565,
      "lon": -0.5070514,
      "alt_m": 22.0
    },
    {
      "lat": 46.2929482,
      "lon": -0.5070962,
      "alt_m": 22.0
    },
    {
      "lat": 46.2929333,
      "lon": -0.5071437,
      "alt_m": 22.0
    },
    {
      "lat": 46.2929148,
      "lon": -0.5071985,
      "alt_m": 22.0
    },
    {
      "lat": 46.2928995,
      "lon": -0.507258,
      "alt_m": 22.0
    },
    {
      "lat": 46.2928929,
      "lon": -0.5073022,
      "alt_m": 22.0
    },
    {
      "lat": 46.29289,
      "lon": -0.5073537,
      "alt_m": 22.0
    },
    {
      "lat": 46.2928914,
      "lon": -0.5073871,
      "alt_m": 22.0
    },
    {
      "lat": 46.2928986,
      "lon": -0.5074249,
      "alt_m": 22.0
    },
    {
      "lat": 46.2929067,
      "lon": -0.5074523,
      "alt_m": 22.0
    },
    {
      "lat": 46.2929194,
      "lon": -0.5074796,
      "alt_m": 22.0
    },
    {
      "lat": 46.2929344,
      "lon": -0.5075058,
      "alt_m": 21.0
    },
    {
      "lat": 46.2929481,
      "lon": -0.5075225,
      "alt_m": 21.0
    },
    {
      "lat": 46.292965,
      "lon": -0.5075393,
      "alt_m": 21.0
    },
    {
      "lat": 46.2929842,
      "lon": -0.5075473,
      "alt_m": 21.0
    },
    {
      "lat": 46.2930064,
      "lon": -0.5075497,
      "alt_m": 21.0
    },
    {
      "lat": 46.2930312,
      "lon": -0.5075441,
      "alt_m": 21.0
    },
    {
      "lat": 46.2930673,
      "lon": -0.5075275,
      "alt_m": 21.0
    },
    {
      "lat": 46.2930964,
      "lon": -0.5075054,
      "alt_m": 21.0
    },
    {
      "lat": 46.2931243,
      "lon": -0.5074816,
      "alt_m": 22.0
    },
    {
      "lat": 46.2931481,
      "lon": -0.5074547,
      "alt_m": 22.0
    },
    {
      "lat": 46.2931707,
      "lon": -0.5074249,
      "alt_m": 22.0
    },
    {
      "lat": 46.293191,
      "lon": -0.5073866,
      "alt_m": 22.0
    },
    {
      "lat": 46.2932051,
      "lon": -0.5073461,
      "alt_m": 22.0
    },
    {
      "lat": 46.2932139,
      "lon": -0.5072931,
      "alt_m": 22.0
    },
    {
      "lat": 46.2932178,
      "lon": -0.507237,
      "alt_m": 22.0
    },
    {
      "lat": 46.2932102,
      "lon": -0.5071708,
      "alt_m": 22.0
    },
    {
      "lat": 46.2931739,
      "lon": -0.5069597,
      "alt_m": 22.0
    },
    {
      "lat": 46.2931448,
      "lon": -0.5068481,
      "alt_m": 22.0
    },
    {
      "lat": 46.2931079,
      "lon": -0.5067251,
      "alt_m": 22.0
    },
    {
      "lat": 46.2930781,
      "lon": -0.5066359,
      "alt_m": 20.0
    },
    {
      "lat": 46.293062,
      "lon": -0.5065948,
      "alt_m": 20.0
    },
    {
      "lat": 46.2930444,
      "lon": -0.506555,
      "alt_m": 20.0
    },
    {
      "lat": 46.2930299,
      "lon": -0.5065242,
      "alt_m": 20.0
    },
    {
      "lat": 46.2930149,
      "lon": -0.5064995,
      "alt_m": 20.0
    },
    {
      "lat": 46.292995,
      "lon": -0.5064775,
      "alt_m": 20.0
    },
    {
      "lat": 46.2929734,
      "lon": -0.5064604,
      "alt_m": 20.0
    },
    {
      "lat": 46.2929501,
      "lon": -0.506447,
      "alt_m": 20.0
    },
    {
      "lat": 46.2929257,
      "lon": -0.5064411,
      "alt_m": 20.0
    },
    {
      "lat": 46.2928983,
      "lon": -0.506441,
      "alt_m": 20.0
    },
    {
      "lat": 46.29287,
      "lon": -0.506444,
      "alt_m": 20.0
    },
    {
      "lat": 46.2928336,
      "lon": -0.5064599,
      "alt_m": 20.0
    },
    {
      "lat": 46.2927888,
      "lon": -0.5064894,
      "alt_m": 20.0
    },
    {
      "lat": 46.2927474,
      "lon": -0.5065254,
      "alt_m": 20.0
    },
    {
      "lat": 46.2927211,
      "lon": -0.5065535,
      "alt_m": 20.0
    },
    {
      "lat": 46.2927036,
      "lon": -0.5065793,
      "alt_m": 20.0
    },
    {
      "lat": 46.2926894,
      "lon": -0.5066061,
      "alt_m": 20.0
    },
    {
      "lat": 46.2926756,
      "lon": -0.5066405,
      "alt_m": 20.0
    },
    {
      "lat": 46.2926626,
      "lon": -0.506678,
      "alt_m": 22.0
    },
    {
      "lat": 46.292644,
      "lon": -0.5067269,
      "alt_m": 22.0
    },
    {
      "lat": 46.2926281,
      "lon": -0.5067601,
      "alt_m": 22.0
    },
    {
      "lat": 46.2926084,
      "lon": -0.5067886,
      "alt_m": 22.0
    },
    {
      "lat": 46.292586,
      "lon": -0.5068117,
      "alt_m": 22.0
    },
    {
      "lat": 46.2925585,
      "lon": -0.5068346,
      "alt_m": 22.0
    },
    {
      "lat": 46.2925349,
      "lon": -0.5068484,
      "alt_m": 22.0
    },
    {
      "lat": 46.2925084,
      "lon": -0.5068583,
      "alt_m": 22.0
    },
    {
      "lat": 46.2924702,
      "lon": -0.5068679,
      "alt_m": 21.0
    },
    {
      "lat": 46.2924335,
      "lon": -0.5068763,
      "alt_m": 21.0
    },
    {
      "lat": 46.2923909,
      "lon": -0.5068879,
      "alt_m": 21.0
    },
    {
      "lat": 46.2923588,
      "lon": -0.5069009,
      "alt_m": 21.0
    },
    {
      "lat": 46.2923313,
      "lon": -0.5069166,
      "alt_m": 21.0
    },
    {
      "lat": 46.2923065,
      "lon": -0.5069372,
      "alt_m": 21.0
    },
    {
      "lat": 46.2916384,
      "lon": -0.5075859,
      "alt_m": 19.0
    },
    {
      "lat": 46.2916204,
      "lon": -0.5076058,
      "alt_m": 19.0
    },
    {
      "lat": 46.2916085,
      "lon": -0.5076221,
      "alt_m": 19.0
    },
    {
      "lat": 46.2916002,
      "lon": -0.5076369,
      "alt_m": 19.0
    },
    {
      "lat": 46.2915917,
      "lon": -0.5076563,
      "alt_m": 19.0
    },
    {
      "lat": 46.291588,
      "lon": -0.5076724,
      "alt_m": 19.0
    },
    {
      "lat": 46.2915876,
      "lon": -0.5076884,
      "alt_m": 19.0
    },
    {
      "lat": 46.291591,
      "lon": -0.5077045,
      "alt_m": 19.0
    },
    {
      "lat": 46.291598,
      "lon": -0.5077232,
      "alt_m": 19.0
    },
    {
      "lat": 46.2916067,
      "lon": -0.5077394,
      "alt_m": 19.0
    },
    {
      "lat": 46.2916184,
      "lon": -0.5077542,
      "alt_m": 19.0
    },
    {
      "lat": 46.2916323,
      "lon": -0.5077664,
      "alt_m": 19.0
    },
    {
      "lat": 46.2916539,
      "lon": -0.5077801,
      "alt_m": 19.0
    },
    {
      "lat": 46.291682,
      "lon": -0.507793,
      "alt_m": 21.0
    },
    {
      "lat": 46.291715,
      "lon": -0.507804,
      "alt_m": 21.0
    },
    {
      "lat": 46.2917584,
      "lon": -0.5078114,
      "alt_m": 21.0
    },
    {
      "lat": 46.2917912,
      "lon": -0.5078134,
      "alt_m": 21.0
    },
    {
      "lat": 46.2918137,
      "lon": -0.507812,
      "alt_m": 21.0
    },
    {
      "lat": 46.2918366,
      "lon": -0.507804,
      "alt_m": 21.0
    },
    {
      "lat": 46.2918552,
      "lon": -0.5077926,
      "alt_m": 21.0
    },
    {
      "lat": 46.2918769,
      "lon": -0.5077737,
      "alt_m": 21.0
    },
    {
      "lat": 46.2918998,
      "lon": -0.5077485,
      "alt_m": 21.0
    },
    {
      "lat": 46.2919202,
      "lon": -0.5077203,
      "alt_m": 21.0
    },
    {
      "lat": 46.2919372,
      "lon": -0.5076924,
      "alt_m": 21.0
    },
    {
      "lat": 46.2919653,
      "lon": -0.5076393,
      "alt_m": 21.0
    },
    {
      "lat": 46.291991,
      "lon": -0.507589,
      "alt_m": 21.0
    },
    {
      "lat": 46.2920166,
      "lon": -0.5075436,
      "alt_m": 21.0
    },
    {
      "lat": 46.2920408,
      "lon": -0.507508,
      "alt_m": 21.0
    },
    {
      "lat": 46.2920685,
      "lon": -0.50747,
      "alt_m": 0.0
    }
  ]
}